Workbook

Sheet Tableau de bord
A1: Tableau de bord – Montée en compétences Contrôle de gestion / Analyse des coûts
A2: Onglet 100 % calculé à partir des onglets Plan et Compétences. Ne rien saisir ici.
A4: Indicateurs globaux
A5: Heures prévues | B5: =Plan!G37 -> 96
A6: Heures réalisées | B6: =Plan!H37 -> 3
A7: Avancement global (heures) | B7: =IFERROR(B6/B5,0) -> 0.03125
A8: Tâches terminées | B8: =COUNTIF(Plan!I5:I36,"Terminé")&" / "&COUNTA(Plan!D5:D36) -> 1 / 32
A9: Niveau moyen actuel (/5) | B9: =Compétences!D18 -> 2
A10: Niveau moyen cible (/5) | B10: =Compétences!E18 -> 4.3846154
A11: Compétences priorité haute | B11: =COUNTIF(Compétences!G5:G17,"Haute") -> 6
A13: Avancement par module
A14: Module | B14: Intitulé | C14: Semaines | D14: Heures prévues | E14: Heures réalisées | F14: % avancement | G14: Tâches | H14: Terminées | I14: Statut
A15: M1 | B15: Comptabilité analytique & coûts | C15: =IF(_xlfn.MINIFS(Plan!$A$5:$A$36,Plan!$B$5:$B$36,A15)=_xlfn.MAXIFS(Plan!$A$5:$A$36,Plan!$B$5:$B$36,A15),_xlfn.MINIFS(Plan!$A$5:$A$36,Plan!$B$5:$B$36,A15)&"",_xlfn.MINIFS(Plan!$A$5:$A$36,Plan!$B$5:$B$36,A15)&"–"&_xlfn.MAXIFS(Plan!$A$5:$A$36,Plan!$B$5:$B$36,A15)) -> 1–2 | D15: =SUMIFS(Plan!$G$5:$G$36,Plan!$B$5:$B$36,A15) -> 12 | E15: =SUMIFS(Plan!$H$5:$H$36,Plan!$B$5:$B$36,A15) -> 3 | F15: =IFERROR(MIN(E15/D15,1),0) -> 0.25 | G15: =COUNTIF(Plan!$B$5:$B$36,A15) -> 4 | H15: =COUNTIFS(Plan!$B$5:$B$36,A15,Plan!$I$5:$I$36,"Terminé") -> 1 | I15: =IF(H15=G15,"Terminé",IF(OR(E15>0,H15>0),"En cours","À faire")) -> En cours
A16: M2 | B16: Excel avancé & Power Query | C16: =IF(_xlfn.MINIFS(Plan!$A$5:$A$36,Plan!$B$5:$B$36,A16)=_xlfn.MAXIFS(Plan!$A$5:$A$36,Plan!$B$5:$B$36,A16),_xlfn.MINIFS(Plan!$A$5:$A$36,Plan!$B$5:$B$36,A16)&"",_xlfn.MINIFS(Plan!$A$5:$A$36,Plan!$B$5:$B$36,A16)&"–"&_xlfn.MAXIFS(Plan!$A$5:$A$36,Plan!$B$5:$B$36,A16)) -> 3–4 | D16: =SUMIFS(Plan!$G$5:$G$36,Plan!$B$5:$B$36,A16) -> 12 | E16: =SUMIFS(Plan!$H$5:$H$36,Plan!$B$5:$B$36,A16) -> 0 | F16: =IFERROR(MIN(E16/D16,1),0) -> 0 | G16: =COUNTIF(Plan!$B$5:$B$36,A16) -> 4 | H16: =COUNTIFS(Plan!$B$5:$B$36,A16,Plan!$I$5:$I$36,"Terminé") -> 0 | I16: =IF(H16=G16,"Terminé",IF(OR(E16>0,H16>0),"En cours","À faire")) -> À faire
A17: M3 | B17: Méthode ABC & inducteurs | C17: =IF(_xlfn.MINIFS(Plan!$A$5:$A$36,Plan!$B$5:$B$36,A17)=_xlfn.MAXIFS(Plan!$A$5:$A$36,Plan!$B$5:$B$36,A17),_xlfn.MINIFS(Plan!$A$5:$A$36,Plan!$B$5:$B$36,A17)&"",_xlfn.MINIFS(Plan!$A$5:$A$36,Plan!$B$5:$B$36,A17)&"–"&_xlfn.MAXIFS(Plan!$A$5:$A$36,Plan!$B$5:$B$36,A17)) -> 5–6 | D17: =SUMIFS(Plan!$G$5:$G$36,Plan!$B$5:$B$36,A17) -> 12 | E17: =SUMIFS(Plan!$H$5:$H$36,Plan!$B$5:$B$36,A17) -> 0 | F17: =IFERROR(MIN(E17/D17,1),0) -> 0 | G17: =COUNTIF(Plan!$B$5:$B$36,A17) -> 4 | H17: =COUNTIFS(Plan!$B$5:$B$36,A17,Plan!$I$5:$I$36,"Terminé") -> 0 | I17: =IF(H17=G17,"Terminé",IF(OR(E17>0,H17>0),"En cours","À faire")) -> À faire
A18: M4 | B18: SAP PCM & outils de répartition | C18: =IF(_xlfn.MINIFS(Plan!$A$5:$A$36,Plan!$B$5:$B$36,A18)=_xlfn.MAXIFS(Plan!$A$5:$A$36,Plan!$B$5:$B$36,A18),_xlfn.MINIFS(Plan!$A$5:$A$36,Plan!$B$5:$B$36,A18)&"",_xlfn.MINIFS(Plan!$A$5:$A$36,Plan!$B$5:$B$36,A18)&"–"&_xlfn.MAXIFS(Plan!$A$5:$A$36,Plan!$B$5:$B$36,A18)) -> 7–8 | D18: =SUMIFS(Plan!$G$5:$G$36,Plan!$B$5:$B$36,A18) -> 12 | E18: =SUMIFS(Plan!$H$5:$H$36,Plan!$B$5:$B$36,A18) -> 0 | F18: =IFERROR(MIN(E18/D18,1),0) -> 0 | G18: =COUNTIF(Plan!$B$5:$B$36,A18) -> 4 | H18: =COUNTIFS(Plan!$B$5:$B$36,A18,Plan!$I$5:$I$36,"Terminé") -> 0 | I18: =IF(H18=G18,"Terminé",IF(OR(E18>0,H18>0),"En cours","À faire")) -> À faire
A19: M5 | B19: Analyse des résultats & bridges | C19: =IF(_xlfn.MINIFS(Plan!$A$5:$A$36,Plan!$B$5:$B$36,A19)=_xlfn.MAXIFS(Plan!$A$5:$A$36,Plan!$B$5:$B$36,A19),_xlfn.MINIFS(Plan!$A$5:$A$36,Plan!$B$5:$B$36,A19)&"",_xlfn.MINIFS(Plan!$A$5:$A$36,Plan!$B$5:$B$36,A19)&"–"&_xlfn.MAXIFS(Plan!$A$5:$A$36,Plan!$B$5:$B$36,A19)) -> 9–10 | D19: =SUMIFS(Plan!$G$5:$G$36,Plan!$B$5:$B$36,A19) -> 12 | E19: =SUMIFS(Plan!$H$5:$H$36,Plan!$B$5:$B$36,A19) -> 0 | F19: =IFERROR(MIN(E19/D19,1),0) -> 0 | G19: =COUNTIF(Plan!$B$5:$B$36,A19) -> 4 | H19: =COUNTIFS(Plan!$B$5:$B$36,A19,Plan!$I$5:$I$36,"Terminé") -> 0 | I19: =IF(H19=G19,"Terminé",IF(OR(E19>0,H19>0),"En cours","À faire")) -> À faire
A20: M6 | B20: Refacturations inter-entités | C20: =IF(_xlfn.MINIFS(Plan!$A$5:$A$36,Plan!$B$5:$B$36,A20)=_xlfn.MAXIFS(Plan!$A$5:$A$36,Plan!$B$5:$B$36,A20),_xlfn.MINIFS(Plan!$A$5:$A$36,Plan!$B$5:$B$36,A20)&"",_xlfn.MINIFS(Plan!$A$5:$A$36,Plan!$B$5:$B$36,A20)&"–"&_xlfn.MAXIFS(Plan!$A$5:$A$36,Plan!$B$5:$B$36,A20)) -> 11 | D20: =SUMIFS(Plan!$G$5:$G$36,Plan!$B$5:$B$36,A20) -> 6 | E20: =SUMIFS(Plan!$H$5:$H$36,Plan!$B$5:$B$36,A20) -> 0 | F20: =IFERROR(MIN(E20/D20,1),0) -> 0 | G20: =COUNTIF(Plan!$B$5:$B$36,A20) -> 2 | H20: =COUNTIFS(Plan!$B$5:$B$36,A20,Plan!$I$5:$I$36,"Terminé") -> 0 | I20: =IF(H20=G20,"Terminé",IF(OR(E20>0,H20>0),"En cours","À faire")) -> À faire
A21: M7 | B21: IFRS 17 & frais attribuables | C21: =IF(_xlfn.MINIFS(Plan!$A$5:$A$36,Plan!$B$5:$B$36,A21)=_xlfn.MAXIFS(Plan!$A$5:$A$36,Plan!$B$5:$B$36,A21),_xlfn.MINIFS(Plan!$A$5:$A$36,Plan!$B$5:$B$36,A21)&"",_xlfn.MINIFS(Plan!$A$5:$A$36,Plan!$B$5:$B$36,A21)&"–"&_xlfn.MAXIFS(Plan!$A$5:$A$36,Plan!$B$5:$B$36,A21)) -> 12–13 | D21: =SUMIFS(Plan!$G$5:$G$36,Plan!$B$5:$B$36,A21) -> 12 | E21: =SUMIFS(Plan!$H$5:$H$36,Plan!$B$5:$B$36,A21) -> 0 | F21: =IFERROR(MIN(E21/D21,1),0) -> 0 | G21: =COUNTIF(Plan!$B$5:$B$36,A21) -> 4 | H21: =COUNTIFS(Plan!$B$5:$B$36,A21,Plan!$I$5:$I$36,"Terminé") -> 0 | I21: =IF(H21=G21,"Terminé",IF(OR(E21>0,H21>0),"En cours","À faire")) -> À faire
A22: M8 | B22: Projet de déploiement d'outil | C22: =IF(_xlfn.MINIFS(Plan!$A$5:$A$36,Plan!$B$5:$B$36,A22)=_xlfn.MAXIFS(Plan!$A$5:$A$36,Plan!$B$5:$B$36,A22),_xlfn.MINIFS(Plan!$A$5:$A$36,Plan!$B$5:$B$36,A22)&"",_xlfn.MINIFS(Plan!$A$5:$A$36,Plan!$B$5:$B$36,A22)&"–"&_xlfn.MAXIFS(Plan!$A$5:$A$36,Plan!$B$5:$B$36,A22)) -> 14 | D22: =SUMIFS(Plan!$G$5:$G$36,Plan!$B$5:$B$36,A22) -> 6 | E22: =SUMIFS(Plan!$H$5:$H$36,Plan!$B$5:$B$36,A22) -> 0 | F22: =IFERROR(MIN(E22/D22,1),0) -> 0 | G22: =COUNTIF(Plan!$B$5:$B$36,A22) -> 2 | H22: =COUNTIFS(Plan!$B$5:$B$36,A22,Plan!$I$5:$I$36,"Terminé") -> 0 | I22: =IF(H22=G22,"Terminé",IF(OR(E22>0,H22>0),"En cours","À faire")) -> À faire
A23: M9 | B23: Études de coûts & restitution | C23: =IF(_xlfn.MINIFS(Plan!$A$5:$A$36,Plan!$B$5:$B$36,A23)=_xlfn.MAXIFS(Plan!$A$5:$A$36,Plan!$B$5:$B$36,A23),_xlfn.MINIFS(Plan!$A$5:$A$36,Plan!$B$5:$B$36,A23)&"",_xlfn.MINIFS(Plan!$A$5:$A$36,Plan!$B$5:$B$36,A23)&"–"&_xlfn.MAXIFS(Plan!$A$5:$A$36,Plan!$B$5:$B$36,A23)) -> 15 | D23: =SUMIFS(Plan!$G$5:$G$36,Plan!$B$5:$B$36,A23) -> 6 | E23: =SUMIFS(Plan!$H$5:$H$36,Plan!$B$5:$B$36,A23) -> 0 | F23: =IFERROR(MIN(E23/D23,1),0) -> 0 | G23: =COUNTIF(Plan!$B$5:$B$36,A23) -> 2 | H23: =COUNTIFS(Plan!$B$5:$B$36,A23,Plan!$I$5:$I$36,"Terminé") -> 0 | I23: =IF(H23=G23,"Terminé",IF(OR(E23>0,H23>0),"En cours","À faire")) -> À faire
A24: M10 | B24: Projet de synthèse | C24: =IF(_xlfn.MINIFS(Plan!$A$5:$A$36,Plan!$B$5:$B$36,A24)=_xlfn.MAXIFS(Plan!$A$5:$A$36,Plan!$B$5:$B$36,A24),_xlfn.MINIFS(Plan!$A$5:$A$36,Plan!$B$5:$B$36,A24)&"",_xlfn.MINIFS(Plan!$A$5:$A$36,Plan!$B$5:$B$36,A24)&"–"&_xlfn.MAXIFS(Plan!$A$5:$A$36,Plan!$B$5:$B$36,A24)) -> 16 | D24: =SUMIFS(Plan!$G$5:$G$36,Plan!$B$5:$B$36,A24) -> 6 | E24: =SUMIFS(Plan!$H$5:$H$36,Plan!$B$5:$B$36,A24) -> 0 | F24: =IFERROR(MIN(E24/D24,1),0) -> 0 | G24: =COUNTIF(Plan!$B$5:$B$36,A24) -> 2 | H24: =COUNTIFS(Plan!$B$5:$B$36,A24,Plan!$I$5:$I$36,"Terminé") -> 0 | I24: =IF(H24=G24,"Terminé",IF(OR(E24>0,H24>0),"En cours","À faire")) -> À faire
A27: Légende : cellules jaunes à texte bleu = saisies · texte noir = formules · texte vert = liens vers un autre onglet.

Sheet Plan
A1: Plan de montée en compétences – 16 semaines (≈ 6 h / semaine)
A2: Saisir uniquement les cellules jaunes (texte bleu) : heures réalisées, statut, date de fin. La ligne 1 (semaine 1) est un exemple rempli.
A4: Semaine | B4: Module | C4: Intitulé module | D4: Tâche / objectif | E4: Ressource | F4: Livrable attendu | G4: Heures prévues | H4: Heures réalisées | I4: Statut | J4: Date de fin | K4: % réalisé
A5: 1 | B5: M1 | C5: Comptabilité analytique & coûts | D5: Charges directes/indirectes, fixes/variables, coût complet vs coût partiel | E5: Alazard & Sépari, DCG 11 (Dunod) – chapitres coûts | F5: Fiche de synthèse 1 page | G5: 3 | H5: 3 | I5: Terminé | J5: 2026-10-25 | K5: =IFERROR(MIN(H5/G5,1),0) -> 1
A6: 1 | B6: M1 | C6: Comptabilité analytique & coûts | D6: Méthode des centres d'analyse : répartition primaire et secondaire | E6: DCG 11 – exercices corrigés | F6: Tableau de répartition sous Excel | G6: 3 | H6: 0 | I6: À faire | K6: =IFERROR(MIN(H6/G6,1),0) -> 0
A7: 2 | B7: M1 | C7: Comptabilité analytique & coûts | D7: Coûts variables, marge sur coût variable, seuil de rentabilité | E7: DCG 11 – chapitre coûts partiels | F7: Mini-modèle Excel de seuil de rentabilité | G7: 3 | H7: 0 | I7: À faire | K7: =IFERROR(MIN(H7/G7,1),0) -> 0
A8: 2 | B8: M1 | C8: Comptabilité analytique & coûts | D8: Frais par destination en assurance (acquisition, administration, sinistres, placements) | E8: Publications France Assureurs / ACPR | F8: Fiche : passage frais par nature → destination | G8: 3 | H8: 0 | I8: À faire | K8: =IFERROR(MIN(H8/G8,1),0) -> 0
A9: 3 | B9: M2 | C9: Excel avancé & Power Query | D9: INDEX/EQUIV, SOMME.SI.ENS, SOMMEPROD, SIERREUR, RECHERCHEX | E9: Exceljet ; Coursera Excel Skills for Business | F9: Classeur d'exercices de formules | G9: 3 | H9: 0 | I9: À faire | K9: =IFERROR(MIN(H9/G9,1),0) -> 0
A10: 3 | B10: M2 | C10: Excel avancé & Power Query | D10: Tableaux croisés dynamiques, segments, mise en forme conditionnelle | E10: Microsoft Support / Learn | F10: TCD des coûts par centre et par nature | G10: 3 | H10: 0 | I10: À faire | K10: =IFERROR(MIN(H10/G10,1),0) -> 0
A11: 4 | B11: M2 | C11: Excel avancé & Power Query | D11: Power Query : import, nettoyage, fusion (balance analytique + volumes) | E11: Microsoft Learn – Power Query | F11: Requête rafraîchissable automatisée | G11: 3 | H11: 0 | I11: À faire | K11: =IFERROR(MIN(H11/G11,1),0) -> 0
A12: 4 | B12: M2 | C12: Excel avancé & Power Query | D12: Modélisation propre : Hypothèses / Calculs / Restitution + contrôles | E12: Ce classeur (structure des onglets) | F12: Modèle avec onglet de contrôles | G12: 3 | H12: 0 | I12: À faire | K12: =IFERROR(MIN(H12/G12,1),0) -> 0
A13: 5 | B13: M3 | C13: Méthode ABC & inducteurs | D13: Théorie ABC : ressources → activités → objets de coût | E13: Alazard & Sépari ; Kaplan & Cooper | F13: Schéma de la chaîne de coûts | G13: 3 | H13: 0 | I13: À faire | K13: =IFERROR(MIN(H13/G13,1),0) -> 0
A14: 5 | B14: M3 | C14: Méthode ABC & inducteurs | D14: Réaliser l'onglet « Exercice ABC », puis modifier les clés et analyser l'impact | E14: Onglet Exercice ABC | F14: Note de 10 lignes sur la sensibilité | G14: 3 | H14: 0 | I14: À faire | K14: =IFERROR(MIN(H14/G14,1),0) -> 0
A15: 6 | B15: M3 | C15: Méthode ABC & inducteurs | D15: Time-Driven ABC : capacité pratique, équations de temps | E15: Kaplan & Anderson, Time-Driven ABC (HBS Press) | F15: Exemple TDABC sur l'activité Prestations | G15: 3 | H15: 0 | I15: À faire | K15: =IFERROR(MIN(H15/G15,1),0) -> 0
A16: 6 | B16: M3 | C16: Méthode ABC & inducteurs | D16: Choisir et documenter un inducteur (pertinence, source, fréquence) | E16: Guide Word – module 3 | F16: Fiche inducteur type (x3) | G16: 3 | H16: 0 | I16: À faire | K16: =IFERROR(MIN(H16/G16,1),0) -> 0
A17: 7 | B17: M4 | C17: SAP PCM & outils de répartition | D17: Logique SAP PCM : modèle, période, version, lignes, activités, assignations | E17: SAP Help Portal ; SAP Learning (PaPM) | F17: Cartographie d'un modèle de répartition | G17: 3 | H17: 0 | I17: À faire | K17: =IFERROR(MIN(H17/G17,1),0) -> 0
... A36: 16 | B36: M10 | C36: Projet de synthèse | D36: Auto-évaluation finale (onglet Compétences) et mise à jour CV / LinkedIn | E36: Onglet Compétences | F36: Profil mis à jour | G36: 2 | H36: 0 | I36: À faire | K36: =IFERROR(MIN(H36/G36,1),0) -> 0
F37: TOTAL | G37: =SUM(G5:G36) -> 96 | H37: =SUM(H5:H36) -> 3 | K37: =IFERROR(H37/G37,0) -> 0.03125

Sheet Compétences
A1: Matrice de compétences – auto-évaluation
A2: Échelle 1 à 5 : 1 = notions · 2 = débutant · 3 = autonome · 4 = maîtrise · 5 = expert (peut former). Ajuster les niveaux actuels (cellules jaunes) — valeurs pré-remplies à titre indicatif.
A4: Compétence | B4: Module | C4: Origine dans le profil | D4: Niveau actuel (1-5) | E4: Niveau cible | F4: Écart | G4: Priorité | H4: Preuve / livrable de validation
A5: Comptabilité analytique (coût complet, centres d'analyse) | B5: M1 | C5: Compétence listée | D5: 2 | E5: 5 | F5: =MAX(E5-D5,0) -> 3 | G5: =IF(F5>=3,"Haute",IF(F5=2,"Moyenne",IF(F5=1,"Basse","Acquise"))) -> Haute | H5: Tableau de répartition commenté
A6: Contrôle de gestion opérationnel | B6: M1 | C6: Expérience STEF | D6: 3 | E6: 4 | F6: =MAX(E6-D6,0) -> 1 | G6: =IF(F6>=3,"Haute",IF(F6=2,"Moyenne",IF(F6=1,"Basse","Acquise"))) -> Basse | H6: Suivi de KPI d'un centre de coûts
A7: Microsoft Excel avancé | B7: M2 | C7: Compétence listée | D7: 3 | E7: 5 | F7: =MAX(E7-D7,0) -> 2 | G7: =IF(F7>=3,"Haute",IF(F7=2,"Moyenne",IF(F7=1,"Basse","Acquise"))) -> Moyenne | H7: Modèle structuré avec contrôles
A8: Power Query / automatisation | B8: M2 | C8: Implicite (traitement de données) | D8: 1 | E8: 4 | F8: =MAX(E8-D8,0) -> 3 | G8: =IF(F8>=3,"Haute",IF(F8=2,"Moyenne",IF(F8=1,"Basse","Acquise"))) -> Haute | H8: Requête rafraîchissable
A9: Méthode ABC – inducteurs de ressources et d'activités | B9: M3 | C9: Missions GGVIE | D9: 2 | E9: 5 | F9: =MAX(E9-D9,0) -> 3 | G9: =IF(F9>=3,"Haute",IF(F9=2,"Moyenne",IF(F9=1,"Basse","Acquise"))) -> Haute | H9: Exercice ABC + note de sensibilité
A10: SAP PCM (répartition des frais généraux) | B10: M4 | C10: Missions GGVIE | D10: 1 | E10: 4 | F10: =MAX(E10-D10,0) -> 3 | G10: =IF(F10>=3,"Haute",IF(F10=2,"Moyenne",IF(F10=1,"Basse","Acquise"))) -> Haute | H10: Cartographie d'un modèle PCM
A11: Réconciliation outil ↔ comptabilité | B11: M4 | C11: Missions GGVIE | D11: 2 | E11: 4 | F11: =MAX(E11-D11,0) -> 2 | G11: =IF(F11>=3,"Haute",IF(F11=2,"Moyenne",IF(F11=1,"Basse","Acquise"))) -> Moyenne | H11: Tableau de bouclage
A12: Analyse des écarts & bridges trimestriels | B12: M5 | C12: Missions GGVIE | D12: 2 | E12: 5 | F12: =MAX(E12-D12,0) -> 3 | G12: =IF(F12>=3,"Haute",IF(F12=2,"Moyenne",IF(F12=1,"Basse","Acquise"))) -> Haute | H12: Bridge + commentaire de gestion
A13: Refacturations inter-entités | B13: M6 | C13: Missions GGVIE | D13: 2 | E13: 4 | F13: =MAX(E13-D13,0) -> 2 | G13: =IF(F13>=3,"Haute",IF(F13=2,"Moyenne",IF(F13=1,"Basse","Acquise"))) -> Moyenne | H13: Tableau de refacturation
A14: IFRS 17 – frais attribuables / IACF | B14: M7 | C14: Missions GGVIE | D14: 1 | E14: 4 | F14: =MAX(E14-D14,0) -> 3 | G14: =IF(F14>=3,"Haute",IF(F14=2,"Moyenne",IF(F14=1,"Basse","Acquise"))) -> Haute | H14: Grille de qualification des frais
A15: Gestion de projet outil (recette, double run) | B15: M8 | C15: Missions GGVIE | D15: 2 | E15: 4 | F15: =MAX(E15-D15,0) -> 2 | G15: =IF(F15>=3,"Haute",IF(F15=2,"Moyenne",IF(F15=1,"Basse","Acquise"))) -> Moyenne | H15: Plan de recette
A16: Études de coûts & restitution (Power BI, storytelling) | B16: M9 | C16: Missions GGVIE | D16: 2 | E16: 4 | F16: =MAX(E16-D16,0) -> 2 | G16: =IF(F16>=3,"Haute",IF(F16=2,"Moyenne",IF(F16=1,"Basse","Acquise"))) -> Moyenne | H16: Étude de coûts restituée
A17: Communication écrite (commentaire de gestion) | B17: M5 | C17: Missions GGVIE | D17: 3 | E17: 5 | F17: =MAX(E17-D17,0) -> 2 | G17: =IF(F17>=3,"Haute",IF(F17=2,"Moyenne",IF(F17=1,"Basse","Acquise"))) -> Moyenne | H17: Note trimestrielle
C18: Moyenne | D18: =AVERAGE(D5:D17) -> 2 | E18: =AVERAGE(E5:E17) -> 4.3846154 | F18: =AVERAGE(F5:F17) -> 2.3846154

Sheet Exercice ABC
A1: Exercice – Répartition des frais généraux par la méthode ABC (cas assurance vie, données fictives)
A2: Modifier les montants, clés et volumes (cellules jaunes) : tout le modèle se recalcule. Objectif : reproduire la logique d'un modèle SAP PCM.
A4: 1. Ressources – frais généraux par nature (k€)
A5: Ressource | B5: Montant (k€)
A6: Salaires et charges | B6: 12000
A7: Loyers et immobilier | B7: 2400
A8: Informatique | B8: 3600
A9: Prestations externes | B9: 1500
A10: Total ressources | B10: =SUM(B6:B9) -> 19500
A12: 2. Inducteurs de ressources – % de chaque ressource consommé par activité
A13: Ressource | B13: Acquisition | C13: Gestion des contrats | D13: Prestations / sinistres | E13: Gestion des placements | F13: Fonctions support | G13: Contrôle (=100 %)
A14: Salaires et charges | B14: 0.25 | C14: 0.3 | D14: 0.25 | E14: 0.08 | F14: 0.12 | G14: =SUM(B14:F14) -> 1
A15: Loyers et immobilier | B15: 0.2 | C15: 0.3 | D15: 0.25 | E15: 0.05 | F15: 0.2 | G15: =SUM(B15:F15) -> 1
A16: Informatique | B16: 0.15 | C16: 0.35 | D16: 0.25 | E16: 0.1 | F16: 0.15 | G16: =SUM(B16:F16) -> 1
A17: Prestations externes | B17: 0.3 | C17: 0.2 | D17: 0.2 | E17: 0.2 | F17: 0.1 | G17: =SUM(B17:F17) -> 1
A18: Coût de l'activité (k€) | B18: =SUMPRODUCT($B$6:$B$9,B14:B17) -> 4470 | C18: =SUMPRODUCT($B$6:$B$9,C14:C17) -> 5880 | D18: =SUMPRODUCT($B$6:$B$9,D14:D17) -> 4800 | E18: =SUMPRODUCT($B$6:$B$9,E14:E17) -> 1740 | F18: =SUMPRODUCT($B$6:$B$9,F14:F17) -> 2610 | G18: =SUM(B18:F18) -> 19500
A19: Attribuable IFRS 17 ? (Oui/Non) | B19: Oui | C19: Oui | D19: Oui | E19: Oui | F19: Non
A21: 3. Inducteurs d'activité – volumes par produit
A22: Activité | B22: Inducteur | C22: Épargne | D22: Prévoyance | E22: Retraite | F22: Total volume | G22: Coût unitaire (k€)
A23: Acquisition | B23: Nb de nouveaux contrats | C23: 8000 | D23: 5000 | E23: 3000 | F23: =SUM(C23:E23) -> 16000 | G23: =IFERROR(B$18/F23,0) -> 0.279375
A24: Gestion des contrats | B24: Nb de contrats en portefeuille | C24: 120000 | D24: 60000 | E24: 40000 | F24: =SUM(C24:E24) -> 220000 | G24: =IFERROR(C$18/F24,0) -> 0.026727273
A25: Prestations / sinistres | B25: Nb de dossiers de prestations | C25: 15000 | D25: 9000 | E25: 6000 | F25: =SUM(C25:E25) -> 30000 | G25: =IFERROR(D$18/F25,0) -> 0.16
A26: Gestion des placements | B26: Encours gérés (M€) | C26: 9000 | D26: 500 | E26: 3500 | F26: =SUM(C26:E26) -> 13000 | G26: =IFERROR(E$18/F26,0) -> 0.13384615
A27: Fonctions support | B27: Nb de contrats en portefeuille | C27: 120000 | D27: 60000 | E27: 40000 | F27: =SUM(C27:E27) -> 220000 | G27: =IFERROR(F$18/F27,0) -> 0.011863636
A29: 4. Coûts affectés aux produits (k€)
A30: Activité | B30: Attribuable IFRS 17 | C30: Épargne | D30: Prévoyance | E30: Retraite | F30: Total
A31: =A23 -> Acquisition | B31: =B19 -> Oui | C31: =C23*$G23 -> 2235 | D31: =D23*$G23 -> 1396.875 | E31: =E23*$G23 -> 838.125 | F31: =SUM(C31:E31) -> 4470
A32: =A24 -> Gestion des contrats | B32: =C19 -> Oui | C32: =C24*$G24 -> 3207.2727 | D32: =D24*$G24 -> 1603.6364 | E32: =E24*$G24 -> 1069.0909 | F32: =SUM(C32:E32) -> 5880
A33: =A25 -> Prestations / sinistres | B33: =D19 -> Oui | C33: =C25*$G25 -> 2400 | D33: =D25*$G25 -> 1440 | E33: =E25*$G25 -> 960 | F33: =SUM(C33:E33) -> 4800
A34: =A26 -> Gestion des placements | B34: =E19 -> Oui | C34: =C26*$G26 -> 1204.6154 | D34: =D26*$G26 -> 66.923077 | E34: =E26*$G26 -> 468.46154 | F34: =SUM(C34:E34) -> 1740
A35: =A27 -> Fonctions support | B35: =F19 -> Non | C35: =C27*$G27 -> 1423.6364 | D35: =D27*$G27 -> 711.81818 | E35: =E27*$G27 -> 474.54545 | F35: =SUM(C35:E35) -> 2610
A36: Total coûts affectés | C36: =SUM(C31:C35) -> 10470.524 | D36: =SUM(D31:D35) -> 5219.2526 | E36: =SUM(E31:E35) -> 3810.2229 | F36: =SUM(F31:F35) -> 19500
A37: dont attribuables IFRS 17 | C37: =SUMIFS(C31:C35,$B$31:$B$35,"Oui") -> 9046.8881 | D37: =SUMIFS(D31:D35,$B$31:$B$35,"Oui") -> 4507.4344 | E37: =SUMIFS(E31:E35,$B$31:$B$35,"Oui") -> 3335.6774 | F37: =SUMIFS(F31:F35,$B$31:$B$35,"Oui") -> 16890
A38: dont non attribuables | C38: =C36-C37 -> 1423.6364 | D38: =D36-D37 -> 711.81818 | E38: =E36-E37 -> 474.54545 | F38: =F36-F37 -> 2610
A39: % attribuable | C39: =IFERROR(C37/C36,0) -> 0.8640339 | D39: =IFERROR(D37/D36,0) -> 0.86361684 | E39: =IFERROR(E37/E36,0) -> 0.87545467 | F39: =IFERROR(F37/F36,0) -> 0.86615385
A41: Contrôle : total affecté – total ressources (doit être « - ») | F41: =ROUND(F36-B10,2) -> 0
A43: Questions : (1) Quel produit porte le plus de frais par contrat ? (2) Que se passe-t-il si l'informatique passe à 45 % sur la gestion des contrats ? (3) Quel est l'impact sur la part attribuable si les placements sont jugés non attribuables ?

Sheet Exercice Bridge
A1: Exercice – Bridge des coûts N-1 → N (direction de gestion, données fictives)
A2: Saisir les inputs N-1 et N (cellules jaunes) puis commenter chaque effet. Le graphique en cascade se met à jour.
A4: Indicateur | B4: N-1 | C4: N | D4: Variation
A5: ETP moyens | B5: 120 | C5: 126 | D5: =C5-B5 -> 6
A6: Coût moyen par ETP (k€) | B6: 68 | C6: 70 | D6: =C6-B6 -> 2
A7: Coûts informatiques (k€) | B7: 3400 | C7: 3750 | D7: =C7-B7 -> 350
A8: Autres frais (k€) | B8: 1900 | C8: 1820 | D8: =C8-B8 -> -80
A9: Éléments non récurrents (k€) | B9: 0 | C9: 250 | D9: =C9-B9 -> 250
A10: Total coûts (k€) | B10: =B5*B6+B7+B8+B9 -> 13460 | C10: =C5*C6+C7+C8+C9 -> 14640 | D10: =C10-B10 -> 1180
A12: Étape du bridge | B12: Montant (k€) | C12: Commentaire (à rédiger) | D12: Cumul | E12: Base (masquée) | F12: Total | G12: Hausse | H12: Baisse
A13: Coûts N-1 | B13: =B10 -> 13460 | D13: =B13 -> 13460 | E13: 0 | F13: =B13 -> 13460 | G13: 0 | H13: 0
A14: Effet volume ETP | B14: =(C5-B5)*B6 -> 408 | C14: Ex. : +6 ETP (renfort projet IFRS 17) valorisés au coût moyen N-1 | D14: =D13+B14 -> 13868 | E14: =MIN(D13,D14) -> 13460 | F14: 0 | G14: =MAX(B14,0) -> 408 | H14: =MAX(-B14,0) -> 0
A15: Effet coût moyen | B15: =(C6-B6)*C5 -> 252 | D15: =D14+B15 -> 14120 | E15: =MIN(D14,D15) -> 13868 | F15: 0 | G15: =MAX(B15,0) -> 252 | H15: =MAX(-B15,0) -> 0
A16: Effet informatique | B16: =C7-B7 -> 350 | D16: =D15+B16 -> 14470 | E16: =MIN(D15,D16) -> 14120 | F16: 0 | G16: =MAX(B16,0) -> 350 | H16: =MAX(-B16,0) -> 0
A17: Effet autres frais | B17: =C8-B8 -> -80 | D17: =D16+B17 -> 14390 | E17: =MIN(D16,D17) -> 14390 | F17: 0 | G17: =MAX(B17,0) -> 0 | H17: =MAX(-B17,0) -> 80
A18: Effet non récurrent | B18: =C9-B9 -> 250 | D18: =D17+B18 -> 14640 | E18: =MIN(D17,D18) -> 14390 | F18: 0 | G18: =MAX(B18,0) -> 250 | H18: =MAX(-B18,0) -> 0
A19: Coûts N | B19: =D18 -> 14640 | D19: =B19 -> 14640 | E19: 0 | F19: =B19 -> 14640 | G19: 0 | H19: 0
A20: Contrôle : Coûts N du bridge – Total N (doit être « - ») | B20: =ROUND(B19-C10,2) -> 0
A22: Méthode : effet volume = ΔETP × coût moyen N-1 ; effet coût moyen = Δcoût moyen × ETP N. La somme des effets explique exactement la variation totale.

Sheet Refacturation
A1: Exercice – Refacturation des services partagés aux entités du groupe (données fictives)
A2: L'entité support refacture ses coûts complets majorés d'une marge, selon des clés de répartition. Cellules jaunes modifiables.
A4: Service | B4: Coût complet (k€) | C4: Clé de répartition | D4: Marge
A5: Informatique | B5: 4000 | C5: Nb de postes de travail | D5: 0.05
A6: RH / Paie | B6: 1200 | C6: Effectif | D6: 0.05
A7: Comptabilité | B7: 900 | C7: Nb d'écritures | D7: 0.05
A8: Juridique | B8: 500 | C8: Temps passé (heures) | D8: 0.05
A10: Volumes de clé par entité | B10: Entité Vie | C10: Entité Prévoyance | D10: Entité Courtage | E10: Total clé
A11: Informatique | B11: 600 | C11: 300 | D11: 100 | E11: =SUM(B11:D11) -> 1000
A12: RH / Paie | B12: 700 | C12: 350 | D12: 150 | E12: =SUM(B12:D12) -> 1200
A13: Comptabilité | B13: 50000 | C13: 20000 | D13: 10000 | E13: =SUM(B13:D13) -> 80000
A14: Juridique | B14: 400 | C14: 250 | D14: 350 | E14: =SUM(B14:D14) -> 1000
A16: Refacturation (k€) | B16: Entité Vie | C16: Entité Prévoyance | D16: Entité Courtage | E16: Total refacturé
A17: Informatique | B17: =IFERROR($B5*(1+$D5)*B11/$E11,0) -> 2520 | C17: =IFERROR($B5*(1+$D5)*C11/$E11,0) -> 1260 | D17: =IFERROR($B5*(1+$D5)*D11/$E11,0) -> 420 | E17: =SUM(B17:D17) -> 4200
A18: RH / Paie | B18: =IFERROR($B6*(1+$D6)*B12/$E12,0) -> 735 | C18: =IFERROR($B6*(1+$D6)*C12/$E12,0) -> 367.5 | D18: =IFERROR($B6*(1+$D6)*D12/$E12,0) -> 157.5 | E18: =SUM(B18:D18) -> 1260
A19: Comptabilité | B19: =IFERROR($B7*(1+$D7)*B13/$E13,0) -> 590.625 | C19: =IFERROR($B7*(1+$D7)*C13/$E13,0) -> 236.25 | D19: =IFERROR($B7*(1+$D7)*D13/$E13,0) -> 118.125 | E19: =SUM(B19:D19) -> 945
A20: Juridique | B20: =IFERROR($B8*(1+$D8)*B14/$E14,0) -> 210 | C20: =IFERROR($B8*(1+$D8)*C14/$E14,0) -> 131.25 | D20: =IFERROR($B8*(1+$D8)*D14/$E14,0) -> 183.75 | E20: =SUM(B20:D20) -> 525
A21: Total refacturé | B21: =SUM(B17:B20) -> 4055.625 | C21: =SUM(C17:C20) -> 1995 | D21: =SUM(D17:D20) -> 879.375 | E21: =SUM(E17:E20) -> 6930
A22: dont marge | E22: =SUMPRODUCT(B5:B8,D5:D8) -> 330
A23: Contrôle : total refacturé – coûts × (1 + marge) | E23: =ROUND(E21-SUMPRODUCT(B5:B8,1+D5:D8),2) -> 0
A25: À retenir : (1) une convention de services formalise clés et marge ; (2) chaque refacturation donne lieu à une facture et une écriture réciproque chez l'entité bénéficiaire ; (3) le rapprochement intragroupe doit être nul à la clôture.

Sheet Ressources
A1: Ressources recommandées
A2: Vérifier les éditions les plus récentes avant achat.
A4: Module | B4: Type | C4: Ressource | D4: Auteur / éditeur | E4: Accès | F4: Usage conseillé
A5: M1-M5 | B5: Livre | C5: DCG 11 – Contrôle de gestion, Manuel et applications | D5: C. Alazard & S. Sépari – Dunod | E5: Payant | F5: Base théorique + exercices corrigés (coûts, ABC, écarts)
A6: M1-M5 | B6: Livre | C6: DSCG 3 – Management et contrôle de gestion | D6: Dunod (plusieurs auteurs) | E6: Payant | F6: Niveau avancé : pilotage, ABC/ABM
A7: M1 | B7: Livre | C7: Le contrôle de gestion | D7: Henri Bouquin – PUF | E7: Payant | F7: Vision d'ensemble du métier
A8: M3 | B8: Livre | C8: Time-Driven Activity-Based Costing | D8: R. S. Kaplan & S. R. Anderson – Harvard Business School Press | E8: Payant | F8: Simplifier un modèle ABC par les temps
A9: M2 | B9: Cours en ligne | C9: Excel Skills for Business (spécialisation) | D9: Macquarie University – coursera.org | E9: Audit gratuit / certificat payant | F9: Excel du niveau essentiel à avancé
A10: M2 | B10: Site | C10: Exceljet – formules et fonctions | D10: exceljet.net | E10: Gratuit | F10: Référence rapide de formules
A11: M2, M9 | B11: Parcours | C11: Power Query & Power BI Data Analyst (PL-300) | D11: Microsoft Learn – learn.microsoft.com | E11: Gratuit (certification payante) | F11: Automatisation et restitution
A12: M4 | B12: Documentation | C12: SAP Profitability and Performance Management (PaPM) | D12: SAP Learning – learning.sap.com ; SAP Help Portal | E12: Gratuit (partiel) | F12: Successeur de SAP PCM : logique de modélisation
A13: M7 | B13: Norme | C13: IFRS 17 Insurance Contracts + documents d'accompagnement | D13: IFRS Foundation – ifrs.org | E13: Gratuit (inscription) | F13: §B65–B66 (flux attribuables), §28A–28F (IACF)
A14: M7 | B14: Publications | C14: Guides IFRS 17 des cabinets d'audit | D14: Big Four (sites publics) | E14: Gratuit | F14: Exemples chiffrés et retours d'expérience
A15: M1, M7 | B15: Site | C15: Publications du secteur assurance | D15: France Assureurs ; ACPR | E15: Gratuit | F15: Contexte réglementaire et données de marché
... A18: Tous | B18: Réseau | C18: DFCG – Association des directeurs financiers et contrôleurs de gestion | D18: dfcg.fr | E18: Adhésion | F18: Veille, conférences, réseau
