Workbook

Sheet Tableau de bord
A1: Tableau de bord – Montée en compétences Consolidation, KPI & audit
A2: Onglet 100 % calculé à partir des onglets Plan et Compétences. Ne rien saisir ici.
A4: Indicateurs globaux
A5: Heures prévues | B5: =Plan!G31 -> 78
A6: Heures réalisées | B6: =Plan!H31 -> 3
A7: Avancement global (heures) | B7: =IFERROR(B6/B5,0) -> 0.038461538
A8: Tâches terminées | B8: =COUNTIF(Plan!I5:I30,"Terminé")&" / "&COUNTA(Plan!D5:D30) -> 1 / 26
A9: Niveau moyen actuel (/5) | B9: =Compétences!D16 -> 2.4545455
A10: Niveau moyen cible (/5) | B10: =Compétences!E16 -> 4.4545455
A11: Compétences priorité haute | B11: =COUNTIF(Compétences!G5:G15,"Haute") -> 2
A13: Avancement par module
A14: Module | B14: Intitulé | C14: Semaines | D14: Heures prévues | E14: Heures réalisées | F14: % avancement | G14: Tâches | H14: Terminées | I14: Statut
A15: C1 | B15: Consolidation des comptes – fondamentaux | C15: =IF(_xlfn.MINIFS(Plan!$A$5:$A$30,Plan!$B$5:$B$30,A15)=_xlfn.MAXIFS(Plan!$A$5:$A$30,Plan!$B$5:$B$30,A15),_xlfn.MINIFS(Plan!$A$5:$A$30,Plan!$B$5:$B$30,A15)&"",_xlfn.MINIFS(Plan!$A$5:$A$30,Plan!$B$5:$B$30,A15)&"–"&_xlfn.MAXIFS(Plan!$A$5:$A$30,Plan!$B$5:$B$30,A15)) -> 1–2 | D15: =SUMIFS(Plan!$G$5:$G$30,Plan!$B$5:$B$30,A15) -> 12 | E15: =SUMIFS(Plan!$H$5:$H$30,Plan!$B$5:$B$30,A15) -> 3 | F15: =IFERROR(MIN(E15/D15,1),0) -> 0.25 | G15: =COUNTIF(Plan!$B$5:$B$30,A15) -> 4 | H15: =COUNTIFS(Plan!$B$5:$B$30,A15,Plan!$I$5:$I$30,"Terminé") -> 1 | I15: =IF(H15=G15,"Terminé",IF(OR(E15>0,H15>0),"En cours","À faire")) -> En cours
A16: C2 | B16: Clôtures mensuelles & fiabilisation | C16: =IF(_xlfn.MINIFS(Plan!$A$5:$A$30,Plan!$B$5:$B$30,A16)=_xlfn.MAXIFS(Plan!$A$5:$A$30,Plan!$B$5:$B$30,A16),_xlfn.MINIFS(Plan!$A$5:$A$30,Plan!$B$5:$B$30,A16)&"",_xlfn.MINIFS(Plan!$A$5:$A$30,Plan!$B$5:$B$30,A16)&"–"&_xlfn.MAXIFS(Plan!$A$5:$A$30,Plan!$B$5:$B$30,A16)) -> 3 | D16: =SUMIFS(Plan!$G$5:$G$30,Plan!$B$5:$B$30,A16) -> 6 | E16: =SUMIFS(Plan!$H$5:$H$30,Plan!$B$5:$B$30,A16) -> 0 | F16: =IFERROR(MIN(E16/D16,1),0) -> 0 | G16: =COUNTIF(Plan!$B$5:$B$30,A16) -> 2 | H16: =COUNTIFS(Plan!$B$5:$B$30,A16,Plan!$I$5:$I$30,"Terminé") -> 0 | I16: =IF(H16=G16,"Terminé",IF(OR(E16>0,H16>0),"En cours","À faire")) -> À faire
A17: C3 | B17: Tagetik & outils de consolidation | C17: =IF(_xlfn.MINIFS(Plan!$A$5:$A$30,Plan!$B$5:$B$30,A17)=_xlfn.MAXIFS(Plan!$A$5:$A$30,Plan!$B$5:$B$30,A17),_xlfn.MINIFS(Plan!$A$5:$A$30,Plan!$B$5:$B$30,A17)&"",_xlfn.MINIFS(Plan!$A$5:$A$30,Plan!$B$5:$B$30,A17)&"–"&_xlfn.MAXIFS(Plan!$A$5:$A$30,Plan!$B$5:$B$30,A17)) -> 4–5 | D17: =SUMIFS(Plan!$G$5:$G$30,Plan!$B$5:$B$30,A17) -> 12 | E17: =SUMIFS(Plan!$H$5:$H$30,Plan!$B$5:$B$30,A17) -> 0 | F17: =IFERROR(MIN(E17/D17,1),0) -> 0 | G17: =COUNTIF(Plan!$B$5:$B$30,A17) -> 4 | H17: =COUNTIFS(Plan!$B$5:$B$30,A17,Plan!$I$5:$I$30,"Terminé") -> 0 | I17: =IF(H17=G17,"Terminé",IF(OR(E17>0,H17>0),"En cours","À faire")) -> À faire
A18: C4 | B18: Intégration de sociétés acquises | C18: =IF(_xlfn.MINIFS(Plan!$A$5:$A$30,Plan!$B$5:$B$30,A18)=_xlfn.MAXIFS(Plan!$A$5:$A$30,Plan!$B$5:$B$30,A18),_xlfn.MINIFS(Plan!$A$5:$A$30,Plan!$B$5:$B$30,A18)&"",_xlfn.MINIFS(Plan!$A$5:$A$30,Plan!$B$5:$B$30,A18)&"–"&_xlfn.MAXIFS(Plan!$A$5:$A$30,Plan!$B$5:$B$30,A18)) -> 6 | D18: =SUMIFS(Plan!$G$5:$G$30,Plan!$B$5:$B$30,A18) -> 6 | E18: =SUMIFS(Plan!$H$5:$H$30,Plan!$B$5:$B$30,A18) -> 0 | F18: =IFERROR(MIN(E18/D18,1),0) -> 0 | G18: =COUNTIF(Plan!$B$5:$B$30,A18) -> 2 | H18: =COUNTIFS(Plan!$B$5:$B$30,A18,Plan!$I$5:$I$30,"Terminé") -> 0 | I18: =IF(H18=G18,"Terminé",IF(OR(E18>0,H18>0),"En cours","À faire")) -> À faire
A19: C5 | B19: Conception d'indicateurs (KPI) | C19: =IF(_xlfn.MINIFS(Plan!$A$5:$A$30,Plan!$B$5:$B$30,A19)=_xlfn.MAXIFS(Plan!$A$5:$A$30,Plan!$B$5:$B$30,A19),_xlfn.MINIFS(Plan!$A$5:$A$30,Plan!$B$5:$B$30,A19)&"",_xlfn.MINIFS(Plan!$A$5:$A$30,Plan!$B$5:$B$30,A19)&"–"&_xlfn.MAXIFS(Plan!$A$5:$A$30,Plan!$B$5:$B$30,A19)) -> 7 | D19: =SUMIFS(Plan!$G$5:$G$30,Plan!$B$5:$B$30,A19) -> 6 | E19: =SUMIFS(Plan!$H$5:$H$30,Plan!$B$5:$B$30,A19) -> 0 | F19: =IFERROR(MIN(E19/D19,1),0) -> 0 | G19: =COUNTIF(Plan!$B$5:$B$30,A19) -> 2 | H19: =COUNTIFS(Plan!$B$5:$B$30,A19,Plan!$I$5:$I$30,"Terminé") -> 0 | I19: =IF(H19=G19,"Terminé",IF(OR(E19>0,H19>0),"En cours","À faire")) -> À faire
A20: C6 | B20: Tableaux de bord & diffusion | C20: =IF(_xlfn.MINIFS(Plan!$A$5:$A$30,Plan!$B$5:$B$30,A20)=_xlfn.MAXIFS(Plan!$A$5:$A$30,Plan!$B$5:$B$30,A20),_xlfn.MINIFS(Plan!$A$5:$A$30,Plan!$B$5:$B$30,A20)&"",_xlfn.MINIFS(Plan!$A$5:$A$30,Plan!$B$5:$B$30,A20)&"–"&_xlfn.MAXIFS(Plan!$A$5:$A$30,Plan!$B$5:$B$30,A20)) -> 8 | D20: =SUMIFS(Plan!$G$5:$G$30,Plan!$B$5:$B$30,A20) -> 6 | E20: =SUMIFS(Plan!$H$5:$H$30,Plan!$B$5:$B$30,A20) -> 0 | F20: =IFERROR(MIN(E20/D20,1),0) -> 0 | G20: =COUNTIF(Plan!$B$5:$B$30,A20) -> 2 | H20: =COUNTIFS(Plan!$B$5:$B$30,A20,Plan!$I$5:$I$30,"Terminé") -> 0 | I20: =IF(H20=G20,"Terminé",IF(OR(E20>0,H20>0),"En cours","À faire")) -> À faire
A21: C7 | B21: Analyse de performance & plans d'actions | C21: =IF(_xlfn.MINIFS(Plan!$A$5:$A$30,Plan!$B$5:$B$30,A21)=_xlfn.MAXIFS(Plan!$A$5:$A$30,Plan!$B$5:$B$30,A21),_xlfn.MINIFS(Plan!$A$5:$A$30,Plan!$B$5:$B$30,A21)&"",_xlfn.MINIFS(Plan!$A$5:$A$30,Plan!$B$5:$B$30,A21)&"–"&_xlfn.MAXIFS(Plan!$A$5:$A$30,Plan!$B$5:$B$30,A21)) -> 9 | D21: =SUMIFS(Plan!$G$5:$G$30,Plan!$B$5:$B$30,A21) -> 6 | E21: =SUMIFS(Plan!$H$5:$H$30,Plan!$B$5:$B$30,A21) -> 0 | F21: =IFERROR(MIN(E21/D21,1),0) -> 0 | G21: =COUNTIF(Plan!$B$5:$B$30,A21) -> 2 | H21: =COUNTIFS(Plan!$B$5:$B$30,A21,Plan!$I$5:$I$30,"Terminé") -> 0 | I21: =IF(H21=G21,"Terminé",IF(OR(E21>0,H21>0),"En cours","À faire")) -> À faire
A22: C8 | B22: Audit financier & contrôle interne | C22: =IF(_xlfn.MINIFS(Plan!$A$5:$A$30,Plan!$B$5:$B$30,A22)=_xlfn.MAXIFS(Plan!$A$5:$A$30,Plan!$B$5:$B$30,A22),_xlfn.MINIFS(Plan!$A$5:$A$30,Plan!$B$5:$B$30,A22)&"",_xlfn.MINIFS(Plan!$A$5:$A$30,Plan!$B$5:$B$30,A22)&"–"&_xlfn.MAXIFS(Plan!$A$5:$A$30,Plan!$B$5:$B$30,A22)) -> 10–11 | D22: =SUMIFS(Plan!$G$5:$G$30,Plan!$B$5:$B$30,A22) -> 12 | E22: =SUMIFS(Plan!$H$5:$H$30,Plan!$B$5:$B$30,A22) -> 0 | F22: =IFERROR(MIN(E22/D22,1),0) -> 0 | G22: =COUNTIF(Plan!$B$5:$B$30,A22) -> 4 | H22: =COUNTIFS(Plan!$B$5:$B$30,A22,Plan!$I$5:$I$30,"Terminé") -> 0 | I22: =IF(H22=G22,"Terminé",IF(OR(E22>0,H22>0),"En cours","À faire")) -> À faire
A23: C9 | B23: Former les collaborateurs | C23: =IF(_xlfn.MINIFS(Plan!$A$5:$A$30,Plan!$B$5:$B$30,A23)=_xlfn.MAXIFS(Plan!$A$5:$A$30,Plan!$B$5:$B$30,A23),_xlfn.MINIFS(Plan!$A$5:$A$30,Plan!$B$5:$B$30,A23)&"",_xlfn.MINIFS(Plan!$A$5:$A$30,Plan!$B$5:$B$30,A23)&"–"&_xlfn.MAXIFS(Plan!$A$5:$A$30,Plan!$B$5:$B$30,A23)) -> 12 | D23: =SUMIFS(Plan!$G$5:$G$30,Plan!$B$5:$B$30,A23) -> 6 | E23: =SUMIFS(Plan!$H$5:$H$30,Plan!$B$5:$B$30,A23) -> 0 | F23: =IFERROR(MIN(E23/D23,1),0) -> 0 | G23: =COUNTIF(Plan!$B$5:$B$30,A23) -> 2 | H23: =COUNTIFS(Plan!$B$5:$B$30,A23,Plan!$I$5:$I$30,"Terminé") -> 0 | I23: =IF(H23=G23,"Terminé",IF(OR(E23>0,H23>0),"En cours","À faire")) -> À faire
A24: C10 | B24: Projet de synthèse | C24: =IF(_xlfn.MINIFS(Plan!$A$5:$A$30,Plan!$B$5:$B$30,A24)=_xlfn.MAXIFS(Plan!$A$5:$A$30,Plan!$B$5:$B$30,A24),_xlfn.MINIFS(Plan!$A$5:$A$30,Plan!$B$5:$B$30,A24)&"",_xlfn.MINIFS(Plan!$A$5:$A$30,Plan!$B$5:$B$30,A24)&"–"&_xlfn.MAXIFS(Plan!$A$5:$A$30,Plan!$B$5:$B$30,A24)) -> 13 | D24: =SUMIFS(Plan!$G$5:$G$30,Plan!$B$5:$B$30,A24) -> 6 | E24: =SUMIFS(Plan!$H$5:$H$30,Plan!$B$5:$B$30,A24) -> 0 | F24: =IFERROR(MIN(E24/D24,1),0) -> 0 | G24: =COUNTIF(Plan!$B$5:$B$30,A24) -> 2 | H24: =COUNTIFS(Plan!$B$5:$B$30,A24,Plan!$I$5:$I$30,"Terminé") -> 0 | I24: =IF(H24=G24,"Terminé",IF(OR(E24>0,H24>0),"En cours","À faire")) -> À faire
A27: Légende : cellules jaunes à texte bleu = saisies · texte noir = formules · texte vert = liens vers un autre onglet.

Sheet Plan
A1: Plan de montée en compétences – Consolidation, KPI & audit – 13 semaines (≈ 6 h / semaine)
A2: Saisir uniquement les cellules jaunes (texte bleu). La ligne 1 est un exemple rempli. Complète le premier plan (contrôle de gestion / analyse des coûts).
A4: Semaine | B4: Module | C4: Intitulé module | D4: Tâche / objectif | E4: Ressource | F4: Livrable attendu | G4: Heures prévues | H4: Heures réalisées | I4: Statut | J4: Date de fin | K4: % réalisé
A5: 1 | B5: C1 | C5: Consolidation des comptes – fondamentaux | D5: Périmètre et méthodes : intégration globale, mise en équivalence, % de contrôle vs % d'intérêts | E5: Obert & Mairesse, DSCG 4 (Dunod) ; règlement ANC 2020-01 | F5: Organigramme du groupe avec méthodes | G5: 3 | H5: 3 | I5: Terminé | J5: 2026-10-25 | K5: =IFERROR(MIN(H5/G5,1),0) -> 1
A6: 1 | B6: C1 | C6: Consolidation des comptes – fondamentaux | D6: Étapes de la consolidation : retraitements, cumul, éliminations, partage des capitaux propres | E6: DSCG 4 – chapitres consolidation | F6: Schéma des étapes | G6: 3 | H6: 0 | I6: À faire | K6: =IFERROR(MIN(H6/G6,1),0) -> 0
A7: 2 | B7: C1 | C7: Consolidation des comptes – fondamentaux | D7: Éliminations intragroupe : ventes, frais, marges sur stocks, dividendes | E7: Onglet Exercice Consolidation | F7: Exercice résolu + 5 lignes de commentaire | G7: 3 | H7: 0 | I7: À faire | K7: =IFERROR(MIN(H7/G7,1),0) -> 0
A8: 2 | B8: C1 | C8: Consolidation des comptes – fondamentaux | D8: Intérêts minoritaires, écart d'acquisition, conversion des comptes en devises (notions) | E8: IFRS 3, IFRS 10, IAS 21 (ifrs.org) | F8: Fiche glossaire consolidation | G8: 3 | H8: 0 | I8: À faire | K8: =IFERROR(MIN(H8/G8,1),0) -> 0
A9: 3 | B9: C2 | C9: Clôtures mensuelles & fiabilisation | D9: Calendrier de clôture J-2 → J+8 : jalons, responsables, livrables | E9: Onglet Clôture mensuelle | F9: Calendrier adapté à votre périmètre | G9: 3 | H9: 0 | I9: À faire | K9: =IFERROR(MIN(H9/G9,1),0) -> 0
A10: 3 | B10: C2 | C10: Clôtures mensuelles & fiabilisation | D10: Contrôles de cohérence des liasses et correction des erreurs ; rapprochements intragroupe | E10: Onglet Exercice Consolidation (section réconciliation) | F10: Check-list de revue de liasse | G10: 3 | H10: 0 | I10: À faire | K10: =IFERROR(MIN(H10/G10,1),0) -> 0
A11: 4 | B11: C3 | C11: Tagetik & outils de consolidation | D11: Logique d'un outil de consolidation : entités, plan de comptes groupe, flux, liasses, règles | E11: Documentation CCH Tagetik (Wolters Kluwer) | F11: Cartographie des objets de l'outil | G11: 3 | H11: 0 | I11: À faire | K11: =IFERROR(MIN(H11/G11,1),0) -> 0
A12: 4 | B12: C3 | C12: Tagetik & outils de consolidation | D12: Workflow de remontée : saisie/import, contrôles bloquants, validation, verrouillage | E12: Documentation éditeur ; retours d'expérience | F12: Schéma du workflow mensuel | G12: 3 | H12: 0 | I12: À faire | K12: =IFERROR(MIN(H12/G12,1),0) -> 0
A13: 5 | B13: C3 | C13: Tagetik & outils de consolidation | D13: Comparer Tagetik, SAP BFC, OneStream, Board : forces, limites, coûts | E13: Sites éditeurs ; publications cabinets | F13: Tableau comparatif | G13: 3 | H13: 0 | I13: À faire | K13: =IFERROR(MIN(H13/G13,1),0) -> 0
A14: 5 | B14: C3 | C14: Tagetik & outils de consolidation | D14: Implémentation d'un projet type ConsAll : paramétrage, reprise historique, recette, bascule | E14: Guide Word – module C3 (+ module M8 du 1er guide) | F14: Plan de projet en 5 lots | G14: 3 | H14: 0 | I14: À faire | K14: =IFERROR(MIN(H14/G14,1),0) -> 0
A15: 6 | B15: C4 | C15: Intégration de sociétés acquises | D15: Intégrer une société acquise : mapping plan de comptes local → groupe et plan analytique | E15: Onglet Exercice Mapping | F15: Table de mapping contrôlée | G15: 3 | H15: 0 | I15: À faire | K15: =IFERROR(MIN(H15/G15,1),0) -> 0
A16: 6 | B16: C4 | C16: Intégration de sociétés acquises | D16: Plan des 100 jours : accès outils, procédures, première liasse, effet périmètre | E16: Guide Word – module C4 | F16: Check-list d'intégration | G16: 3 | H16: 0 | I16: À faire | K16: =IFERROR(MIN(H16/G16,1),0) -> 0
A17: 7 | B17: C5 | C17: Conception d'indicateurs (KPI) | D17: Concevoir un KPI : objectif, formule, source, fréquence, cible, seuils, responsable | E17: Fernandez, Les nouveaux tableaux de bord des managers (Eyrolles) | F17: 3 fiches indicateurs | G17: 3 | H17: 0 | I17: À faire | K17: =IFERROR(MIN(H17/G17,1),0) -> 0
... A30: 13 | B30: C10 | C30: Projet de synthèse | D30: Auto-évaluation finale et mise à jour du CV / LinkedIn | E30: Onglet Compétences | F30: Profil mis à jour | G30: 2 | H30: 0 | I30: À faire | K30: =IFERROR(MIN(H30/G30,1),0) -> 0
F31: TOTAL | G31: =SUM(G5:G30) -> 78 | H31: =SUM(H5:H30) -> 3 | K31: =IFERROR(H31/G31,0) -> 0.038461538

Sheet Compétences
A1: Matrice de compétences – auto-évaluation (nouvelles compétences uniquement)
A2: Échelle 1 à 5 : 1 = notions · 2 = débutant · 3 = autonome · 4 = maîtrise · 5 = expert. Niveaux actuels pré-remplis à titre indicatif : à ajuster.
A4: Compétence | B4: Module | C4: Origine dans le profil | D4: Niveau actuel (1-5) | E4: Niveau cible | F4: Écart | G4: Priorité | H4: Preuve / livrable de validation
A5: Consolidation des comptes (périmètre, méthodes, étapes) | B5: C1 | C5: Consolidation des données du groupe | D5: 2 | E5: 4 | F5: =MAX(E5-D5,0) -> 2 | G5: =IF(F5>=3,"Haute",IF(F5=2,"Moyenne",IF(F5=1,"Basse","Acquise"))) -> Moyenne | H5: Exercice consolidation résolu
A6: Éliminations et réconciliations intragroupe | B6: C1 | C6: Correction des erreurs pour la consolidation | D6: 2 | E6: 5 | F6: =MAX(E6-D6,0) -> 3 | G6: =IF(F6>=3,"Haute",IF(F6=2,"Moyenne",IF(F6=1,"Basse","Acquise"))) -> Haute | H6: Tableau de réconciliation
A7: Clôtures mensuelles & fiabilisation des liasses | B7: C2 | C7: Suivi des clôtures mensuelles | D7: 3 | E7: 5 | F7: =MAX(E7-D7,0) -> 2 | G7: =IF(F7>=3,"Haute",IF(F7=2,"Moyenne",IF(F7=1,"Basse","Acquise"))) -> Moyenne | H7: Calendrier + check-list de revue
A8: CCH Tagetik / outil de consolidation | B8: C3 | C8: Projet ConsAll (Tagetik) | D8: 2 | E8: 4 | F8: =MAX(E8-D8,0) -> 2 | G8: =IF(F8>=3,"Haute",IF(F8=2,"Moyenne",IF(F8=1,"Basse","Acquise"))) -> Moyenne | H8: Cartographie de l'outil + plan de projet
A9: Intégration analytique de sociétés acquises | B9: C4 | C9: Intégration suite aux rachats | D9: 2 | E9: 4 | F9: =MAX(E9-D9,0) -> 2 | G9: =IF(F9>=3,"Haute",IF(F9=2,"Moyenne",IF(F9=1,"Basse","Acquise"))) -> Moyenne | H9: Table de mapping contrôlée
A10: Conception d'indicateurs de performance | B10: C5 | C10: Mise en place de KPI (réunions transverses) | D10: 3 | E10: 5 | F10: =MAX(E10-D10,0) -> 2 | G10: =IF(F10>=3,"Haute",IF(F10=2,"Moyenne",IF(F10=1,"Basse","Acquise"))) -> Moyenne | H10: Fiches indicateurs + arbre de KPI
A11: Tableaux de bord & diffusion mensuelle | B11: C6 | C11: Création et diffusion des tableaux de bord | D11: 3 | E11: 5 | F11: =MAX(E11-D11,0) -> 2 | G11: =IF(F11>=3,"Haute",IF(F11=2,"Moyenne",IF(F11=1,"Basse","Acquise"))) -> Moyenne | H11: Tableau de bord dynamique
A12: Analyse des causes & plans d'actions correctives | B12: C7 | C12: Solutions en cas d'écarts négatifs | D12: 2 | E12: 5 | F12: =MAX(E12-D12,0) -> 3 | G12: =IF(F12>=3,"Haute",IF(F12=2,"Moyenne",IF(F12=1,"Basse","Acquise"))) -> Haute | H12: Pareto + plan d'actions
A13: Audit financier & contrôle interne des filiales | B13: C8 | C13: Audit des bonnes pratiques comptables | D13: 2 | E13: 4 | F13: =MAX(E13-D13,0) -> 2 | G13: =IF(F13>=3,"Haute",IF(F13=2,"Moyenne",IF(F13=1,"Basse","Acquise"))) -> Moyenne | H13: Rapport d'audit
A14: Formation des collaborateurs | B14: C9 | C14: Formation aux logiciels comptable et conso | D14: 3 | E14: 4 | F14: =MAX(E14-D14,0) -> 1 | G14: =IF(F14>=3,"Haute",IF(F14=2,"Moyenne",IF(F14=1,"Basse","Acquise"))) -> Basse | H14: Déroulé pédagogique + aide-mémoire
A15: Animation de réunions transverses | B15: C5 | C15: Réunions transverses | D15: 3 | E15: 4 | F15: =MAX(E15-D15,0) -> 1 | G15: =IF(F15>=3,"Haute",IF(F15=2,"Moyenne",IF(F15=1,"Basse","Acquise"))) -> Basse | H15: Compte rendu d'atelier KPI
C16: Moyenne | D16: =AVERAGE(D5:D15) -> 2.4545455 | E16: =AVERAGE(E5:E15) -> 4.4545455 | F16: =AVERAGE(F5:F15) -> 2
A18: Déjà couvert par le premier plan (non repris ici) : Excel avancé, Power Query, bases Power BI, calcul des écarts / bridges, gestion de projet de déploiement d'outil, analyse de données.

Sheet Exercice Consolidation
A1: Exercice – Consolidation du compte de résultat d'un mini-groupe (données fictives, k€)
A2: Mère M détient F1 à 100 % et F2 à 80 % (intégration globale). Charges en négatif. Modifier les cellules jaunes : tout se recalcule.
A4: 1. Hypothèses des opérations intragroupe
A5: Ventes de M à F1 (k€) | B5: 500
A6: Frais de gestion facturés par M à F2 (k€) | B6: 120
A7: Stock chez F1 acheté à M, en fin de période (k€) | B7: 200
A8: Taux de marge de M sur ses ventes (% du prix de vente) | B8: 0.25
A9: Taux d'impôt sur les sociétés | B9: 0.25
A10: % d'intérêts du groupe dans F2 | B10: 0.8
A12: 2. Comptes individuels, éliminations et compte de résultat consolidé
A13: Poste (k€) | B13: Mère M | C13: Filiale F1 | D13: Filiale F2 | E13: Cumul | F13: Élim. ventes M→F1 | G13: Élim. frais de gestion | H13: Élim. marge sur stock | I13: Consolidé
A14: Chiffre d'affaires | B14: 10000 | C14: 4000 | D14: 2500 | E14: =SUM(B14:D14) -> 16500 | F14: =-B5 -> -500 | G14: =-B6 -> -120 | H14: 0 | I14: =SUM(E14:H14) -> 15880
A15: Achats consommés | B15: -6000 | C15: -2500 | D15: -1300 | E15: =SUM(B15:D15) -> -9800 | F15: =B5 -> 500 | G15: 0 | H15: =-B7*B8 -> -50 | I15: =SUM(E15:H15) -> -9350
A16: Charges externes | B16: -1200 | C16: -500 | D16: -400 | E16: =SUM(B16:D16) -> -2100 | F16: 0 | G16: =B6 -> 120 | H16: 0 | I16: =SUM(E16:H16) -> -1980
A17: Charges de personnel | B17: -1800 | C17: -700 | D17: -500 | E17: =SUM(B17:D17) -> -3000 | F17: 0 | G17: 0 | H17: 0 | I17: =SUM(E17:H17) -> -3000
A18: Impôt sur les résultats | B18: -250 | C18: -75 | D18: -75 | E18: =SUM(B18:D18) -> -400 | F18: 0 | G18: 0 | H18: =B7*B8*B9 -> 12.5 | I18: =SUM(E18:H18) -> -387.5
A19: Résultat net | B19: =SUM(B14:B18) -> 750 | C19: =SUM(C14:C18) -> 225 | D19: =SUM(D14:D18) -> 225 | E19: =SUM(E14:E18) -> 1200 | F19: =SUM(F14:F18) -> 0 | G19: =SUM(G14:G18) -> 0 | H19: =SUM(H14:H18) -> -37.5 | I19: =SUM(I14:I18) -> 1162.5
A21: Intérêts minoritaires (quote-part de F2) | I21: =D19*(1-B10) -> 45
A22: Résultat net – part du groupe | I22: =I19-I21 -> 1117.5
A23: Contrôle : éliminations ventes et frais sans impact sur le résultat (doit être « - ») | I23: =F19+G19 -> 0
A25: 3. Réconciliation des soldes intragroupe à la clôture
A26: Seuil de tolérance (k€) | B26: 1
A27: Couple / nature | B27: Créance chez | C27: Montant créance | D27: Dette chez | E27: Montant dette | F27: Écart | G27: Statut | H27: Explication (à rédiger)
A28: M / F1 – clients / fournisseurs | B28: M | C28: 500 | D28: F1 | E28: 480 | F28: =C28-E28 -> 20 | G28: =IF(ABS(F28)<=$B$26,"OK","À analyser") -> À analyser | H28: Ex. : facture de 20 k€ en transit, reçue par F1 le mois suivant
A29: M / F2 – frais de gestion | B29: M | C29: 120 | D29: F2 | E29: 120 | F29: =C29-E29 -> 0 | G29: =IF(ABS(F29)<=$B$26,"OK","À analyser") -> OK
A30: F1 / F2 – prêt intragroupe | B30: F1 | C30: 300 | D30: F2 | E30: 300 | F30: =C30-E30 -> 0 | G30: =IF(ABS(F30)<=$B$26,"OK","À analyser") -> OK
A31: F2 / M – refacturation de personnel | B31: F2 | C31: 45 | D31: M | E31: 38 | F31: =C31-E31 -> 7 | G31: =IF(ABS(F31)<=$B$26,"OK","À analyser") -> À analyser
A32: Nombre d'écarts à analyser | G32: =COUNTIF(G28:G31,"À analyser") -> 2
A34: Questions : (1) Pourquoi l'élimination des ventes ne change-t-elle pas le résultat ? (2) Que devient la marge sur stock si F1 a tout revendu ? (3) Comment traiter l'écart F2 / M de 7 k€ avant la remontée de la liasse ?

Sheet Exercice Mapping
A1: Exercice – Intégrer une société acquise : mapping plan de comptes local → plan de comptes groupe
A2: 1) Compléter la table de mapping (cellules jaunes). 2) Vérifier qu'aucun compte n'est « Non mappé ». 3) Contrôler que le total groupe = total local.
A4: Compte local | B4: Libellé local | C4: Solde (k€) | D4: Compte groupe | E4: Libellé groupe | H4: Compte groupe | I4: Libellé groupe | J4: Total agrégé (k€)
A5: 601000 | B5: Achats matières premières | C5: 820 | D5: G-ACH | E5: =IF(D5="","Non mappé",IFERROR(INDEX($I$5:$I$10,MATCH(D5,$H$5:$H$10,0)),"Code inconnu")) -> Achats consommés | H5: G-ACH | I5: Achats consommés | J5: =SUMIFS($C$5:$C$16,$D$5:$D$16,H5) -> 915
A6: 602200 | B6: Achats emballages | C6: 95 | D6: G-ACH | E6: =IF(D6="","Non mappé",IFERROR(INDEX($I$5:$I$10,MATCH(D6,$H$5:$H$10,0)),"Code inconnu")) -> Achats consommés | H6: G-EXT | I6: Charges externes | J6: =SUMIFS($C$5:$C$16,$D$5:$D$16,H6) -> 323
A7: 604000 | B7: Sous-traitance | C7: 60 | D7: G-EXT | E7: =IF(D7="","Non mappé",IFERROR(INDEX($I$5:$I$10,MATCH(D7,$H$5:$H$10,0)),"Code inconnu")) -> Charges externes | H7: G-PER | I7: Charges de personnel | J7: =SUMIFS($C$5:$C$16,$D$5:$D$16,H7) -> 860
A8: 606100 | B8: Énergie | C8: 140 | D8: G-EXT | E8: =IF(D8="","Non mappé",IFERROR(INDEX($I$5:$I$10,MATCH(D8,$H$5:$H$10,0)),"Code inconnu")) -> Charges externes | H8: G-AMO | I8: Dotations aux amortissements | J8: =SUMIFS($C$5:$C$16,$D$5:$D$16,H8) -> 120
A9: 613200 | B9: Locations immobilières | C9: 75 | D9: G-EXT | E9: =IF(D9="","Non mappé",IFERROR(INDEX($I$5:$I$10,MATCH(D9,$H$5:$H$10,0)),"Code inconnu")) -> Charges externes | H9: G-FIN | I9: Résultat financier | J9: =SUMIFS($C$5:$C$16,$D$5:$D$16,H9) -> 22
A10: 622600 | B10: Honoraires | C10: 30 | D10: G-EXT | E10: =IF(D10="","Non mappé",IFERROR(INDEX($I$5:$I$10,MATCH(D10,$H$5:$H$10,0)),"Code inconnu")) -> Charges externes | H10: G-IS | I10: Impôt sur les résultats | J10: =SUMIFS($C$5:$C$16,$D$5:$D$16,H10) -> 0
A11: 625100 | B11: Déplacements | C11: 18 | D11: G-EXT | E11: =IF(D11="","Non mappé",IFERROR(INDEX($I$5:$I$10,MATCH(D11,$H$5:$H$10,0)),"Code inconnu")) -> Charges externes | I11: Total groupe | J11: =SUM(J5:J10) -> 2240
A12: 641100 | B12: Salaires | C12: 610 | D12: G-PER | E12: =IF(D12="","Non mappé",IFERROR(INDEX($I$5:$I$10,MATCH(D12,$H$5:$H$10,0)),"Code inconnu")) -> Charges de personnel | I12: Comptes non mappés | J12: =COUNTIF(E5:E16,"Non mappé")+COUNTIF(E5:E16,"Code inconnu") -> 1
A13: 645100 | B13: Charges sociales | C13: 250 | D13: G-PER | E13: =IF(D13="","Non mappé",IFERROR(INDEX($I$5:$I$10,MATCH(D13,$H$5:$H$10,0)),"Code inconnu")) -> Charges de personnel | I13: Écart total local – groupe | J13: =C17-J11 -> 35
A14: 681100 | B14: Dotations aux amortissements | C14: 120 | D14: G-AMO | E14: =IF(D14="","Non mappé",IFERROR(INDEX($I$5:$I$10,MATCH(D14,$H$5:$H$10,0)),"Code inconnu")) -> Dotations aux amortissements
A15: 661100 | B15: Intérêts d'emprunts | C15: 22 | D15: G-FIN | E15: =IF(D15="","Non mappé",IFERROR(INDEX($I$5:$I$10,MATCH(D15,$H$5:$H$10,0)),"Code inconnu")) -> Résultat financier
A16: 695000 | B16: Impôt sur les bénéfices | C16: 35 | E16: =IF(D16="","Non mappé",IFERROR(INDEX($I$5:$I$10,MATCH(D16,$H$5:$H$10,0)),"Code inconnu")) -> Non mappé
B17: Total local | C17: =SUM(C5:C16) -> 2275
A20: Bon réflexe : un contrôle « comptes non mappés = 0 » et « écart = 0 » est bloquant avant toute remontée dans l'outil de consolidation. La même logique s'applique au plan analytique (centres de coûts locaux → axes groupe).

Sheet KPI Données
A1: Données mensuelles des indicateurs – filiale agroalimentaire (fictif)
A2: Budget et réel par mois. Saisir le réel chaque mois (cellules jaunes) : le tableau de bord se met à jour. Réel connu jusqu'en septembre.
A4: BUDGET – Indicateur | B4: Unité | C4: Sens favorable | D4: Agrégation | E4: Janv. | F4: Févr. | G4: Mars | H4: Avr. | I4: Mai | J4: Juin | K4: Juil. | L4: Août | M4: Sept. | N4: Oct. | O4: Nov. | P4: Déc.
A5: Chiffre d'affaires | B5: k€ | C5: Hausse | D5: Somme | E5: 2000 | F5: 2000 | G5: 2000 | H5: 2080 | I5: 2080 | J5: 2000 | K5: 2000 | L5: 2000 | M5: 2000 | N5: 2000 | O5: 2080 | P5: 2080
A6: Taux de marge brute | B6: % | C6: Hausse | D6: Moyenne | E6: 0.22 | F6: 0.22 | G6: 0.22 | H6: 0.22 | I6: 0.22 | J6: 0.22 | K6: 0.22 | L6: 0.22 | M6: 0.22 | N6: 0.22 | O6: 0.22 | P6: 0.22
A7: Coût de revient | B7: €/kg | C7: Baisse | D7: Moyenne | E7: 3.1 | F7: 3.1 | G7: 3.1 | H7: 3.1 | I7: 3.1 | J7: 3.1 | K7: 3.1 | L7: 3.1 | M7: 3.1 | N7: 3.1 | O7: 3.1 | P7: 3.1
A8: Volumes produits | B8: t | C8: Hausse | D8: Somme | E8: 650 | F8: 650 | G8: 650 | H8: 676 | I8: 676 | J8: 650 | K8: 650 | L8: 650 | M8: 650 | N8: 650 | O8: 676 | P8: 676
A9: Taux de service client | B9: % | C9: Hausse | D9: Moyenne | E9: 0.97 | F9: 0.97 | G9: 0.97 | H9: 0.97 | I9: 0.97 | J9: 0.97 | K9: 0.97 | L9: 0.97 | M9: 0.97 | N9: 0.97 | O9: 0.97 | P9: 0.97
A10: Taux d'absentéisme | B10: % | C10: Baisse | D10: Moyenne | E10: 0.055 | F10: 0.055 | G10: 0.055 | H10: 0.055 | I10: 0.055 | J10: 0.055 | K10: 0.055 | L10: 0.055 | M10: 0.055 | N10: 0.055 | O10: 0.055 | P10: 0.055
A11: DSO (délai de paiement clients) | B11: jours | C11: Baisse | D11: Moyenne | E11: 45 | F11: 45 | G11: 45 | H11: 45 | I11: 45 | J11: 45 | K11: 45 | L11: 45 | M11: 45 | N11: 45 | O11: 45 | P11: 45
A14: RÉEL – Indicateur | B14: Unité | C14: Sens favorable | D14: Agrégation | E14: Janv. | F14: Févr. | G14: Mars | H14: Avr. | I14: Mai | J14: Juin | K14: Juil. | L14: Août | M14: Sept. | N14: Oct. | O14: Nov. | P14: Déc.
A15: Chiffre d'affaires | B15: k€ | C15: Hausse | D15: Somme | E15: 1974.6319 | F15: 1949.7223 | G15: 2021.7346 | H15: 2015.9681 | I15: 2085.3737 | J15: 1980.6592 | K15: 1936.3518 | L15: 2001.0707 | M15: 1933.3994
A16: Taux de marge brute | B16: % | C16: Hausse | D16: Moyenne | E16: 0.2191 | F16: 0.2143 | G16: 0.2146 | H16: 0.219 | I16: 0.2243 | J16: 0.215 | K16: 0.2097 | L16: 0.2151 | M16: 0.2193
A17: Coût de revient | B17: €/kg | C17: Baisse | D17: Moyenne | E17: 3.1086 | F17: 3.0885 | G17: 3.1532 | H17: 3.0494 | I17: 3.14 | J17: 3.0765 | K17: 3.1161 | L17: 3.1131 | M17: 3.1344
A18: Volumes produits | B18: t | C18: Hausse | D18: Somme | E18: 662.3289 | F18: 637.5483 | G18: 653.1824 | H18: 681.6343 | I18: 670.8244 | J18: 651.862 | K18: 632.9488 | L18: 632.8244 | M18: 638.5324
A19: Taux de service client | B19: % | C19: Hausse | D19: Moyenne | E19: 0.9731 | F19: 0.9687 | G19: 0.9668 | H19: 0.9715 | I19: 0.9692 | J19: 0.9665 | K19: 0.9664 | L19: 0.9647 | M19: 0.9568
A20: Taux d'absentéisme | B20: % | C20: Baisse | D20: Moyenne | E20: 0.0556 | F20: 0.0552 | G20: 0.058 | H20: 0.0568 | I20: 0.0533 | J20: 0.0588 | K20: 0.052 | L20: 0.0544 | M20: 0.057
A21: DSO (délai de paiement clients) | B21: jours | C21: Baisse | D21: Moyenne | E21: 43.4966 | F21: 44.9523 | G21: 43.0094 | H21: 45.7267 | I21: 46.1429 | J21: 45.3155 | K21: 46.6221 | L21: 44.1954 | M21: 45.8437

Sheet Tableau de bord KPI
A1: Tableau de bord mensuel – Filiale agroalimentaire (fictif)
A2: Choisir le mois (cellule jaune). Feux : vert = conforme ou favorable · orange = défavorable dans la tolérance · rouge = défavorable au-delà.
A4: Mois de reporting (1-12) | B4: 9 | C4: =INDEX('KPI Données'!$E$4:$P$4,1,B4) -> Sept.
A5: Tolérance orange (écart défavorable max.) | B5: 0.03
A7: Indicateur | B7: Unité | C7: Sens | D7: Budget mois | E7: Réel mois | F7: Écart | G7: Écart % | H7: Feu | I7: Budget cumul | J7: Réel cumul | K7: Écart cumul % | L7: Feu cumul
A8: ='KPI Données'!A15 -> Chiffre d'affaires | B8: ='KPI Données'!B15 -> k€ | C8: ='KPI Données'!C15 -> Hausse | D8: =INDEX('KPI Données'!$E$5:$P$5,1,$B$4) -> 2000 | E8: =INDEX('KPI Données'!$E$15:$P$15,1,$B$4) -> 1933.3994 | F8: =E8-D8 -> -66.6006 | G8: =IFERROR(F8/D8,0) -> -0.0333003 | H8: =IF(E8="","n.d.",IF(G8*IF(C8="Hausse",1,-1)>=0,"Vert",IF(G8*IF(C8="Hausse",1,-1)>=-$B$5,"Orange","Rouge"))) -> Rouge | I8: =SUMPRODUCT((COLUMN('KPI Données'!$E$5:$P$5)-COLUMN('KPI Données'!$E$5)+1<=$B$4)*'KPI Données'!$E$5:$P$5)/IF('KPI Données'!$D$15="Somme",1,$B$4) -> 18160 | J8: =SUMPRODUCT((COLUMN('KPI Données'!$E$5:$P$5)-COLUMN('KPI Données'!$E$5)+1<=$B$4)*'KPI Données'!$E$15:$P$15)/IF('KPI Données'!$D$15="Somme",1,$B$4) -> 17898.912 | K8: =IFERROR((J8-I8)/I8,0) -> -0.014377109 | L8: =IF(K8*IF(C8="Hausse",1,-1)>=0,"Vert",IF(K8*IF(C8="Hausse",1,-1)>=-$B$5,"Orange","Rouge")) -> Orange
A9: ='KPI Données'!A16 -> Taux de marge brute | B9: ='KPI Données'!B16 -> % | C9: ='KPI Données'!C16 -> Hausse | D9: =INDEX('KPI Données'!$E$6:$P$6,1,$B$4) -> 0.22 | E9: =INDEX('KPI Données'!$E$16:$P$16,1,$B$4) -> 0.2193 | F9: =E9-D9 -> -0.0007 | G9: =IFERROR(F9/D9,0) -> -0.0031818182 | H9: =IF(E9="","n.d.",IF(G9*IF(C9="Hausse",1,-1)>=0,"Vert",IF(G9*IF(C9="Hausse",1,-1)>=-$B$5,"Orange","Rouge"))) -> Orange | I9: =SUMPRODUCT((COLUMN('KPI Données'!$E$6:$P$6)-COLUMN('KPI Données'!$E$6)+1<=$B$4)*'KPI Données'!$E$6:$P$6)/IF('KPI Données'!$D$16="Somme",1,$B$4) -> 0.22 | J9: =SUMPRODUCT((COLUMN('KPI Données'!$E$6:$P$6)-COLUMN('KPI Données'!$E$6)+1<=$B$4)*'KPI Données'!$E$16:$P$16)/IF('KPI Données'!$D$16="Somme",1,$B$4) -> 0.21671111 | K9: =IFERROR((J9-I9)/I9,0) -> -0.014949495 | L9: =IF(K9*IF(C9="Hausse",1,-1)>=0,"Vert",IF(K9*IF(C9="Hausse",1,-1)>=-$B$5,"Orange","Rouge")) -> Orange
A10: ='KPI Données'!A17 -> Coût de revient | B10: ='KPI Données'!B17 -> €/kg | C10: ='KPI Données'!C17 -> Baisse | D10: =INDEX('KPI Données'!$E$7:$P$7,1,$B$4) -> 3.1 | E10: =INDEX('KPI Données'!$E$17:$P$17,1,$B$4) -> 3.1344 | F10: =E10-D10 -> 0.0344 | G10: =IFERROR(F10/D10,0) -> 0.011096774 | H10: =IF(E10="","n.d.",IF(G10*IF(C10="Hausse",1,-1)>=0,"Vert",IF(G10*IF(C10="Hausse",1,-1)>=-$B$5,"Orange","Rouge"))) -> Orange | I10: =SUMPRODUCT((COLUMN('KPI Données'!$E$7:$P$7)-COLUMN('KPI Données'!$E$7)+1<=$B$4)*'KPI Données'!$E$7:$P$7)/IF('KPI Données'!$D$17="Somme",1,$B$4) -> 3.1 | J10: =SUMPRODUCT((COLUMN('KPI Données'!$E$7:$P$7)-COLUMN('KPI Données'!$E$7)+1<=$B$4)*'KPI Données'!$E$17:$P$17)/IF('KPI Données'!$D$17="Somme",1,$B$4) -> 3.1088667 | K10: =IFERROR((J10-I10)/I10,0) -> 0.0028602151 | L10: =IF(K10*IF(C10="Hausse",1,-1)>=0,"Vert",IF(K10*IF(C10="Hausse",1,-1)>=-$B$5,"Orange","Rouge")) -> Orange
A11: ='KPI Données'!A18 -> Volumes produits | B11: ='KPI Données'!B18 -> t | C11: ='KPI Données'!C18 -> Hausse | D11: =INDEX('KPI Données'!$E$8:$P$8,1,$B$4) -> 650 | E11: =INDEX('KPI Données'!$E$18:$P$18,1,$B$4) -> 638.5324 | F11: =E11-D11 -> -11.4676 | G11: =IFERROR(F11/D11,0) -> -0.017642462 | H11: =IF(E11="","n.d.",IF(G11*IF(C11="Hausse",1,-1)>=0,"Vert",IF(G11*IF(C11="Hausse",1,-1)>=-$B$5,"Orange","Rouge"))) -> Orange | I11: =SUMPRODUCT((COLUMN('KPI Données'!$E$8:$P$8)-COLUMN('KPI Données'!$E$8)+1<=$B$4)*'KPI Données'!$E$8:$P$8)/IF('KPI Données'!$D$18="Somme",1,$B$4) -> 5902 | J11: =SUMPRODUCT((COLUMN('KPI Données'!$E$8:$P$8)-COLUMN('KPI Données'!$E$8)+1<=$B$4)*'KPI Données'!$E$18:$P$18)/IF('KPI Données'!$D$18="Somme",1,$B$4) -> 5861.6859 | K11: =IFERROR((J11-I11)/I11,0) -> -0.0068305829 | L11: =IF(K11*IF(C11="Hausse",1,-1)>=0,"Vert",IF(K11*IF(C11="Hausse",1,-1)>=-$B$5,"Orange","Rouge")) -> Orange
A12: ='KPI Données'!A19 -> Taux de service client | B12: ='KPI Données'!B19 -> % | C12: ='KPI Données'!C19 -> Hausse | D12: =INDEX('KPI Données'!$E$9:$P$9,1,$B$4) -> 0.97 | E12: =INDEX('KPI Données'!$E$19:$P$19,1,$B$4) -> 0.9568 | F12: =E12-D12 -> -0.0132 | G12: =IFERROR(F12/D12,0) -> -0.013608247 | H12: =IF(E12="","n.d.",IF(G12*IF(C12="Hausse",1,-1)>=0,"Vert",IF(G12*IF(C12="Hausse",1,-1)>=-$B$5,"Orange","Rouge"))) -> Orange | I12: =SUMPRODUCT((COLUMN('KPI Données'!$E$9:$P$9)-COLUMN('KPI Données'!$E$9)+1<=$B$4)*'KPI Données'!$E$9:$P$9)/IF('KPI Données'!$D$19="Somme",1,$B$4) -> 0.97 | J12: =SUMPRODUCT((COLUMN('KPI Données'!$E$9:$P$9)-COLUMN('KPI Données'!$E$9)+1<=$B$4)*'KPI Données'!$E$19:$P$19)/IF('KPI Données'!$D$19="Somme",1,$B$4) -> 0.96707778 | K12: =IFERROR((J12-I12)/I12,0) -> -0.0030126002 | L12: =IF(K12*IF(C12="Hausse",1,-1)>=0,"Vert",IF(K12*IF(C12="Hausse",1,-1)>=-$B$5,"Orange","Rouge")) -> Orange
A13: ='KPI Données'!A20 -> Taux d'absentéisme | B13: ='KPI Données'!B20 -> % | C13: ='KPI Données'!C20 -> Baisse | D13: =INDEX('KPI Données'!$E$10:$P$10,1,$B$4) -> 0.055 | E13: =INDEX('KPI Données'!$E$20:$P$20,1,$B$4) -> 0.057 | F13: =E13-D13 -> 0.002 | G13: =IFERROR(F13/D13,0) -> 0.036363636 | H13: =IF(E13="","n.d.",IF(G13*IF(C13="Hausse",1,-1)>=0,"Vert",IF(G13*IF(C13="Hausse",1,-1)>=-$B$5,"Orange","Rouge"))) -> Rouge | I13: =SUMPRODUCT((COLUMN('KPI Données'!$E$10:$P$10)-COLUMN('KPI Données'!$E$10)+1<=$B$4)*'KPI Données'!$E$10:$P$10)/IF('KPI Données'!$D$20="Somme",1,$B$4) -> 0.055 | J13: =SUMPRODUCT((COLUMN('KPI Données'!$E$10:$P$10)-COLUMN('KPI Données'!$E$10)+1<=$B$4)*'KPI Données'!$E$20:$P$20)/IF('KPI Données'!$D$20="Somme",1,$B$4) -> 0.055677778 | K13: =IFERROR((J13-I13)/I13,0) -> 0.012323232 | L13: =IF(K13*IF(C13="Hausse",1,-1)>=0,"Vert",IF(K13*IF(C13="Hausse",1,-1)>=-$B$5,"Orange","Rouge")) -> Orange
A14: ='KPI Données'!A21 -> DSO (délai de paiement clients) | B14: ='KPI Données'!B21 -> jours | C14: ='KPI Données'!C21 -> Baisse | D14: =INDEX('KPI Données'!$E$11:$P$11,1,$B$4) -> 45 | E14: =INDEX('KPI Données'!$E$21:$P$21,1,$B$4) -> 45.8437 | F14: =E14-D14 -> 0.8437 | G14: =IFERROR(F14/D14,0) -> 0.018748889 | H14: =IF(E14="","n.d.",IF(G14*IF(C14="Hausse",1,-1)>=0,"Vert",IF(G14*IF(C14="Hausse",1,-1)>=-$B$5,"Orange","Rouge"))) -> Orange | I14: =SUMPRODUCT((COLUMN('KPI Données'!$E$11:$P$11)-COLUMN('KPI Données'!$E$11)+1<=$B$4)*'KPI Données'!$E$11:$P$11)/IF('KPI Données'!$D$21="Somme",1,$B$4) -> 45 | J14: =SUMPRODUCT((COLUMN('KPI Données'!$E$11:$P$11)-COLUMN('KPI Données'!$E$11)+1<=$B$4)*'KPI Données'!$E$21:$P$21)/IF('KPI Données'!$D$21="Somme",1,$B$4) -> 45.033844 | K14: =IFERROR((J14-I14)/I14,0) -> 0.00075209877 | L14: =IF(K14*IF(C14="Hausse",1,-1)>=0,"Vert",IF(K14*IF(C14="Hausse",1,-1)>=-$B$5,"Orange","Rouge")) -> Orange
A16: Indicateurs au rouge ce mois | B16: =COUNTIF(H8:H14,"Rouge") -> 2
A17: Commentaire du mois (à rédiger) | B17: Ex. : dérive du coût de revient depuis juillet (+1 % vs budget en septembre) liée au prix des matières ; voir plan d'actions.

Sheet Plan d'actions
A1: Analyse des écarts négatifs : Pareto des causes et plan d'actions correctives (fictif)
A2: Cas : le coût de revient dépasse le budget depuis juillet (environ +1 %). Les causes sont classées par impact décroissant (loi 80/20).
A4: Cause identifiée | B4: Impact annuel estimé (k€) | C4: % du total | D4: % cumulé | E4: Classe
A5: Hausse du prix des matières premières | B5: 310 | C5: =IFERROR(B5/$B$12,0) -> 0.40789474 | D5: =SUM($C$5:C5) -> 0.40789474 | E5: =IF(D5-C5<0.8,"A",IF(D5-C5<0.95,"B","C")) -> A | F5: Classe A : causes qui expliquent ~80 % de l'écart → priorité des actions.
A6: Rendement matière dégradé (pertes) | B6: 180 | C6: =IFERROR(B6/$B$12,0) -> 0.23684211 | D6: =SUM($C$5:C6) -> 0.64473684 | E6: =IF(D6-C6<0.8,"A",IF(D6-C6<0.95,"B","C")) -> A
A7: Heures supplémentaires / intérim | B7: 120 | C7: =IFERROR(B7/$B$12,0) -> 0.15789474 | D7: =SUM($C$5:C7) -> 0.80263158 | E7: =IF(D7-C7<0.8,"A",IF(D7-C7<0.95,"B","C")) -> A
A8: Arrêts de ligne non planifiés | B8: 75 | C8: =IFERROR(B8/$B$12,0) -> 0.098684211 | D8: =SUM($C$5:C8) -> 0.90131579 | E8: =IF(D8-C8<0.8,"A",IF(D8-C8<0.95,"B","C")) -> B
A9: Coût de l'énergie | B9: 40 | C9: =IFERROR(B9/$B$12,0) -> 0.052631579 | D9: =SUM($C$5:C9) -> 0.95394737 | E9: =IF(D9-C9<0.8,"A",IF(D9-C9<0.95,"B","C")) -> B
A10: Emballages non conformes | B10: 20 | C10: =IFERROR(B10/$B$12,0) -> 0.026315789 | D10: =SUM($C$5:C10) -> 0.98026316 | E10: =IF(D10-C10<0.8,"A",IF(D10-C10<0.95,"B","C")) -> C
A11: Divers | B11: 15 | C11: =IFERROR(B11/$B$12,0) -> 0.019736842 | D11: =SUM($C$5:C11) -> 1 | E11: =IF(D11-C11<0.8,"A",IF(D11-C11<0.95,"B","C")) -> C
A12: Total | B12: =SUM(B5:B11) -> 760
A14: Plan d'actions correctives
A15: Cause (classe A/B) | B15: Action | C15: Responsable | D15: Échéance | E15: Statut | F15: Gain annuel attendu (k€) | G15: Gain constaté (k€) | H15: Indicateur de suivi
A16: Hausse du prix des matières premières | B16: Renégocier les contrats d'achat et indexer les prix de vente | C16: Directeur achats | D16: 2026-12-31 | E16: En cours | F16: 150 | G16: 40 | H16: Prix moyen d'achat €/kg
A17: Rendement matière dégradé (pertes) | B17: Suivi quotidien des pertes par ligne + formation opérateurs | C17: Responsable production | D17: 2026-11-30 | E17: À faire | F17: 90 | G17: 0 | H17: Rendement matière %
A18: Heures supplémentaires / intérim | B18: Revoir la planification des équipes selon les volumes | C18: Responsable RH site | D18: 2026-11-15 | E18: À faire | F18: 60 | G18: 0 | H18: Heures sup. / mois
E19: À faire | F19: 0 | G19: 0
E20: À faire | F20: 0 | G20: 0
A21: Total gains | F21: =SUM(F16:F20) -> 300 | G21: =SUM(G16:G20) -> 40
A22: Couverture de l'écart par les gains attendus | F22: =IFERROR(F21/B12,0) -> 0.39473684
A23: Actions terminées | F23: =COUNTIF(E16:E20,"Terminé")&" / "&COUNTA(B16:B20) -> 0 / 3

Sheet Audit filiales
A1: Grille d'audit des bonnes pratiques comptables – filiales (exemple pré-rempli)
A2: Pour chaque point : Conforme / Non conforme / N.A. Le score exclut les N.A. Exemple fictif à remplacer par vos constats.
A4: Cycle | B4: Point de contrôle | C4: Risque couvert | D4: Test à réaliser | E4: Filiale A | F4: Filiale B | G4: Filiale C
A5: Clôture | B5: Calendrier de clôture respecté (liasse remontée à J+5) | C5: Retard de consolidation | D5: Comparer dates de remontée vs calendrier | E5: Conforme | F5: Non conforme | G5: Conforme
A6: Clôture | B6: Revue analytique mensuelle documentée | C6: Erreurs non détectées | D6: Obtenir la revue et les justifications d'écarts | E6: Conforme | F6: Conforme | G6: Non conforme
A7: Achats | B7: Séparation des tâches commande / réception / paiement | C7: Fraude, paiements indus | D7: Revoir les droits utilisateurs ERP | E7: Conforme | F7: Non conforme | G7: Non conforme
A8: Achats | B8: Factures non parvenues provisionnées | C8: Charges sous-évaluées | D8: Tester les réceptions non facturées | E8: Conforme | F8: Conforme | G8: Conforme
A9: Ventes | B9: Rapprochement livraisons / facturation | C9: CA non facturé ou fictif | D9: Échantillon de 25 bons de livraison | E9: Conforme | F9: Conforme | G9: Non conforme
A10: Ventes | B10: Balance âgée clients revue et provisions justifiées | C10: Créances douteuses non provisionnées | D10: Analyser les créances > 90 jours | E10: Non conforme | F10: Conforme | G10: Conforme
A11: Stocks | B11: Inventaire physique et traitement des écarts | C11: Stock surévalué | D11: Assister à un inventaire tournant | E11: Conforme | F11: Conforme | G11: N.A.
A12: Stocks | B12: Valorisation au coût de revient à jour | C12: Marge erronée | D12: Recalculer 10 coûts de revient | E12: Conforme | F12: Non conforme | G12: N.A.
A13: Trésorerie | B13: Rapprochements bancaires mensuels signés | C13: Détournement, erreurs | D13: Vérifier les 3 derniers rapprochements | E13: Conforme | F13: Conforme | G13: Conforme
A14: Trésorerie | B14: Pouvoirs bancaires à jour | C14: Paiements non autorisés | D14: Comparer pouvoirs et organigramme | E14: Conforme | F14: Conforme | G14: Non conforme
A15: Paie | B15: Contrôle des variables de paie avant validation | C15: Erreurs de paie | D15: Revoir le contrôle sur 2 mois | E15: Conforme | F15: Conforme | G15: Conforme
... A19: Analytique | B19: Mapping comptes / centres conforme au référentiel groupe | C19: Reporting faussé | D19: Contrôler les comptes non mappés | E19: Conforme | F19: Non conforme | G19: Conforme
D20: Points conformes | E20: =COUNTIF(E5:E19,"Conforme") -> 13 | F20: =COUNTIF(F5:F19,"Conforme") -> 10 | G20: =COUNTIF(G5:G19,"Conforme") -> 8
D21: Points non conformes | E21: =COUNTIF(E5:E19,"Non conforme") -> 1 | F21: =COUNTIF(F5:F19,"Non conforme") -> 5 | G21: =COUNTIF(G5:G19,"Non conforme") -> 5
D22: Score de conformité | E22: =IFERROR(E20/(E20+E21),0) -> 0.92857143 | F22: =IFERROR(F20/(F20+F21),0) -> 0.66666667 | G22: =IFERROR(G20/(G20+G21),0) -> 0.61538462
D23: Appréciation | E23: =IF(E22>=0.9,"Satisfaisant",IF(E22>=0.75,"À améliorer","Insuffisant")) -> Satisfaisant | F23: =IF(F22>=0.9,"Satisfaisant",IF(F22>=0.75,"À améliorer","Insuffisant")) -> Insuffisant | G23: =IF(G22>=0.9,"Satisfaisant",IF(G22>=0.75,"À améliorer","Insuffisant")) -> Insuffisant

Sheet Clôture mensuelle
A1: Calendrier type de clôture mensuelle et de consolidation
A2: Adapter les jours au calendrier de votre groupe. Mettre à jour les statuts chaque mois.
A4: Jour | B4: Étape | C4: Responsable | D4: Livrable / contrôle | E4: Statut
A5: J-2 | B5: Cut-off : arrêt des saisies achats/ventes, envoi des instructions de clôture | C5: Filiales / groupe | D5: Instructions envoyées | E5: Terminé
A6: J-1 | B6: Pré-rapprochement des soldes intragroupe | C6: Filiales | D6: Confirmations intragroupe | E6: À faire
A7: J+1 | B7: Écritures d'inventaire : FNP, CCA, provisions, stocks | C7: Filiales | D7: Balance provisoire | E7: À faire
A8: J+2 | B8: Rapprochements bancaires et revue analytique locale | C8: Filiales | D8: Justifications d'écarts | E8: À faire
A9: J+3 | B9: Remontée des liasses dans l'outil de consolidation | C9: Filiales | D9: Liasse soumise, contrôles bloquants OK | E9: À faire
A10: J+4 | B10: Revue des liasses par le groupe, corrections | C10: Contrôle de gestion groupe | D10: Liasses validées | E10: À faire
A11: J+5 | B11: Éliminations intragroupe et traitements de consolidation | C11: Consolidation groupe | D11: Écarts intragroupe soldés | E11: À faire
A12: J+6 | B12: Analyse des résultats consolidés vs budget et N-1 | C12: Contrôle de gestion groupe | D12: Bridge et commentaires | E12: À faire
A13: J+7 | B13: Production du tableau de bord consolidé | C13: Contrôle de gestion groupe | D13: Tableau de bord | E13: À faire
A14: J+8 | B14: Diffusion au comité de direction, plan d'actions | C14: Contrôle de gestion groupe | D14: Tableau de bord diffusé | E14: À faire
D15: Avancement de la clôture | E15: =COUNTIF(E5:E14,"Terminé")/COUNTA(B5:B14) -> 0.1

Sheet Ressources
A1: Ressources recommandées
A2: Vérifier les éditions les plus récentes avant achat.
A4: Module | B4: Type | C4: Ressource | D4: Auteur / éditeur | E4: Accès | F4: Usage conseillé
A5: C1, C8 | B5: Livre | C5: DSCG 4 – Comptabilité et audit, Manuel et applications | D5: R. Obert & M.-P. Mairesse – Dunod | E5: Payant | F5: Consolidation (règles françaises) et audit
A6: C1 | B6: Livre | C6: Pratique des normes IFRS | D6: Robert Obert – Dunod | E6: Payant | F6: Consolidation en IFRS (IFRS 3, 10, 11, IAS 21)
A7: C1 | B7: Réglementation | C7: Règlement ANC n° 2020-01 relatif aux comptes consolidés | D7: Autorité des normes comptables – anc.gouv.fr | E7: Gratuit | F7: Règles françaises de consolidation
A8: C1 | B8: Normes | C8: IFRS 10, IFRS 3, IAS 21 | D8: IFRS Foundation – ifrs.org | E8: Gratuit (inscription) | F8: Contrôle, regroupements, conversion
A9: C3 | B9: Éditeur | C9: CCH Tagetik – documentation et formations | D9: Wolters Kluwer | E9: Selon licence | F9: Paramétrage, workflow, consolidation
A10: C5 | B10: Livre | C10: The Balanced Scorecard | D10: R. S. Kaplan & D. P. Norton – Harvard Business School Press | E10: Payant | F10: Relier stratégie et indicateurs
A11: C5, C6 | B11: Livre | C11: Les nouveaux tableaux de bord des managers | D11: Alain Fernandez – Eyrolles | E11: Payant | F11: Méthode de conception de tableaux de bord
A12: C6 | B12: Livre | C12: Information Dashboard Design | D12: Stephen Few – Analytics Press | E12: Payant | F12: Lisibilité et design des tableaux de bord
A13: C8 | B13: Référentiel | C13: Internal Control – Integrated Framework (2013) | D13: COSO – coso.org | E13: Synthèse gratuite | F13: Cadre du contrôle interne
A14: C8 | B14: Référentiel | C14: Cadre de référence du contrôle interne | D14: AMF – amf-france.org | E14: Gratuit | F14: Version française appliquée aux sociétés
A15: C8 | B15: Réseau | C15: IFACI – Institut français de l'audit et du contrôle internes | D15: ifaci.com | E15: Adhésion / formations | F15: Méthodes d'audit, certifications
... A17: Rappel | B17: Plan 1 | C17: Excel, Power Query, Power BI, écarts, gestion de projet | D17: Voir le premier classeur | E17: - | F17: Compétences déjà couvertes
